{"version": 0.6, "generator": "Overpass API 0.7.62.10 2d4cfc48", "osm3s": {"timestamp_osm_base": "2026-01-29T01:53:33Z", "copyright": "The data included in this document is from www.openstreetmap.org. The data is made available under ODbL."}, "elements": [{"type": "node", "id": 155911269, "lat": 38.717114, "lon": -79.97718}, {"type": "node", "id": 155914586, "lat": 38.6646913, "lon": -79.9272347}, {"type": "node", "id": 155914857, "lat": 38.731642, "lon": -79.9699009}, {"type": "node", "id": 155915648, "lat": 38.7845709, "lon": -79.9072778}, {"type": "node", "id": 155916508, "lat": 38.771975, "lon": -79.9310338}, {"type": "node", "id": 155917085, "lat": 38.750442, "lon": -79.958628}, {"type": "node", "id": 155922465, "lat": 38.7592732, "lon": -79.9532905}, {"type": "node", "id": 155924892, "lat": 38.6944788, "lon": -79.9744849}, {"type": "node", "id": 155925485, "lat": 38.68114, "lon": -79.9709213}, {"type": "node", "id": 155925502, "lat": 38.6797999, "lon": -79.9672069}, {"type": "node", "id": 155925689, "lat": 38.6774228, "lon": -79.9606589}, {"type": "node", "id": 155926098, "lat": 38.7335689, "lon": -79.9696344}, {"type": "node", "id": 155928956, "lat": 38.6753887, "lon": -79.9514975}, {"type": "node", "id": 155928995, "lat": 38.6673422, "lon": -79.9417462}, {"type": "node", "id": 155929258, "lat": 38.6846079, "lon": -79.9739637}, {"type": "node", "id": 155930407, "lat": 38.771766, "lon": -79.937796}, {"type": "node", "id": 155930442, "lat": 38.7720581, "lon": -79.9284501}, {"type": "node", "id": 155932662, "lat": 38.7431012, "lon": -79.9645266}, {"type": "node", "id": 155936538, "lat": 38.7807053, "lon": -79.9136088}, {"type": "node", "id": 155936581, "lat": 38.7963541, "lon": -79.8999216}, {"type": "node", "id": 155944107, "lat": 38.722354, "lon": -79.973765}, {"type": "node", "id": 155946641, "lat": 38.77204, "lon": -79.934045}, {"type": "node", "id": 155946655, "lat": 38.7720357, "lon": -79.9330699}, {"type": "node", "id": 155949982, "lat": 38.6816213, "lon": -79.9719763}, {"type": "node", "id": 155950348, "lat": 38.7663989, "lon": -79.9475581}, {"type": "node", "id": 155950574, "lat": 38.660803, "lon": -79.936442}, {"type": "node", "id": 155953484, "lat": 38.71651, "lon": -79.977837}, {"type": "node", "id": 155954739, "lat": 38.7861937, "lon": -79.9066757}, {"type": "node", "id": 155957661, "lat": 38.659063, "lon": -79.934019}, {"type": "node", "id": 155959444, "lat": 38.720185, "lon": -79.974817}, {"type": "node", "id": 155962519, "lat": 38.7307861, "lon": -79.9704144}, {"type": "node", "id": 155966963, "lat": 38.7129084, "lon": -79.9793544}, {"type": "node", "id": 155971229, "lat": 38.732976, "lon": -79.9696571}, {"type": "node", "id": 155973068, "lat": 38.7288542, "lon": -79.9715548}, {"type": "node", "id": 155975060, "lat": 38.7312377, "lon": -79.9701265}, {"type": "node", "id": 155975976, "lat": 38.7717983, "lon": -79.9253992}, {"type": "node", "id": 155976352, "lat": 38.6513019, "lon": -79.9218605}, {"type": "node", "id": 155976353, "lat": 38.6520525, "lon": -79.9229485}, {"type": "node", "id": 155976354, "lat": 38.6527627, "lon": -79.9234155}, {"type": "node", "id": 155976355, "lat": 38.6533001, "lon": -79.9233123}, {"type": "node", "id": 155976356, "lat": 38.6536456, "lon": -79.923037}, {"type": "node", "id": 155976358, "lat": 38.6539105, "lon": -79.9226536}, {"type": "node", "id": 155976360, "lat": 38.654517, "lon": -79.9211592}, {"type": "node", "id": 155976362, "lat": 38.6545977, "lon": -79.921056}, {"type": "node", "id": 155976365, "lat": 38.6550123, "lon": -79.9208643}, {"type": "node", "id": 155976366, "lat": 38.6555919, "lon": -79.9211395}, {"type": "node", "id": 155976367, "lat": 38.6581524, "lon": -79.923622}, {"type": "node", "id": 155976369, "lat": 38.6586066, "lon": -79.9240424}, {"type": "node", "id": 155976371, "lat": 38.658971, "lon": -79.924241}, {"type": "node", "id": 155976373, "lat": 38.6593587, "lon": -79.9241402}, {"type": "node", "id": 155976375, "lat": 38.6594694, "lon": -79.9240375}, {"type": "node", "id": 155976378, "lat": 38.6595953, "lon": -79.9223705}, {"type": "node", "id": 155976380, "lat": 38.6596182, "lon": -79.9221505}, {"type": "node", "id": 155976382, "lat": 38.6601412, "lon": -79.9216714}, {"type": "node", "id": 155976384, "lat": 38.6605039, "lon": -79.9218865}, {"type": "node", "id": 155976386, "lat": 38.6606527, "lon": -79.9220674}, {"type": "node", "id": 155976388, "lat": 38.6618514, "lon": -79.9246877}, {"type": "node", "id": 155976390, "lat": 38.6618399, "lon": -79.926125}, {"type": "node", "id": 155976392, "lat": 38.6619201, "lon": -79.926736}, {"type": "node", "id": 155976394, "lat": 38.6622331, "lon": -79.927132}, {"type": "node", "id": 155976400, "lat": 38.6626224, "lon": -79.9272249}, {"type": "node", "id": 155976401, "lat": 38.662798, "lon": -79.9271956}, {"type": "node", "id": 155976402, "lat": 38.6641569, "lon": -79.9267507}, {"type": "node", "id": 155976403, "lat": 38.664405, "lon": -79.9267849}, {"type": "node", "id": 155976404, "lat": 38.6645959, "lon": -79.926956}, {"type": "node", "id": 155976406, "lat": 38.6646646, "lon": -79.9270978}, {"type": "node", "id": 155976408, "lat": 38.6643478, "lon": -79.9278506}, {"type": "node", "id": 155976410, "lat": 38.6639394, "lon": -79.9279973}, {"type": "node", "id": 155976411, "lat": 38.6633744, "lon": -79.9281831}, {"type": "node", "id": 155976414, "lat": 38.659916, "lon": -79.9293514}, {"type": "node", "id": 155976416, "lat": 38.6595228, "lon": -79.9296154}, {"type": "node", "id": 155976417, "lat": 38.6590838, "lon": -79.9301287}, {"type": "node", "id": 155976418, "lat": 38.658828, "lon": -79.9306909}, {"type": "node", "id": 155976420, "lat": 38.6586639, "lon": -79.932309}, {"type": "node", "id": 155976422, "lat": 38.660231, "lon": -79.9358}, {"type": "node", "id": 155976424, "lat": 38.660693, "lon": -79.936318}, {"type": "node", "id": 155976426, "lat": 38.66072, "lon": -79.936348}, {"type": "node", "id": 155976428, "lat": 38.661673, "lon": -79.936997}, {"type": "node", "id": 155976430, "lat": 38.6637777, "lon": -79.9381191}, {"type": "node", "id": 155976432, "lat": 38.6644788, "lon": -79.9385581}, {"type": "node", "id": 155976434, "lat": 38.6647444, "lon": -79.9387713}, {"type": "node", "id": 155976436, "lat": 38.6653944, "lon": -79.9394351}, {"type": "node", "id": 155976448, "lat": 38.6751208, "lon": -79.9510397}, {"type": "node", "id": 155976450, "lat": 38.6754885, "lon": -79.9516999}, {"type": "node", "id": 155976451, "lat": 38.6755776, "lon": -79.9519096}, {"type": "node", "id": 155976453, "lat": 38.6769163, "lon": -79.9588194}, {"type": "node", "id": 155976454, "lat": 38.6771692, "lon": -79.9599044}, {"type": "node", "id": 155976456, "lat": 38.6810341, "lon": -79.9706318}, {"type": "node", "id": 155976476, "lat": 38.7091938, "lon": -79.9785446}, {"type": "node", "id": 155976480, "lat": 38.711064, "lon": -79.97901}, {"type": "node", "id": 155978186, "lat": 38.7321544, "lon": -79.9697152}, {"type": "node", "id": 155978452, "lat": 38.726056, "lon": -79.973228}, {"type": "node", "id": 155980907, "lat": 38.7678874, "lon": -79.9458997}, {"type": "node", "id": 155982295, "lat": 38.7719448, "lon": -79.9300668}, {"type": "node", "id": 155985461, "lat": 38.7738611, "lon": -79.9210792}, {"type": "node", "id": 155987402, "lat": 38.7969812, "lon": -79.8989408}, {"type": "node", "id": 155988204, "lat": 38.7833699, "lon": -79.9099297}, {"type": "node", "id": 155988336, "lat": 38.7728671, "lon": -79.9226892}, {"type": "node", "id": 155990366, "lat": 38.7147562, "lon": -79.979035}, {"type": "node", "id": 155990370, "lat": 38.717738, "lon": -79.976616}, {"type": "node", "id": 155990372, "lat": 38.719208, "lon": -79.975477}, {"type": "node", "id": 155990374, "lat": 38.721323, "lon": -79.973966}, {"type": "node", "id": 155990376, "lat": 38.721573, "lon": -79.973859}, {"type": "node", "id": 155990378, "lat": 38.72224, "lon": -79.973791}, {"type": "node", "id": 155990380, "lat": 38.722677, "lon": -79.973753}, {"type": "node", "id": 155990382, "lat": 38.723815, "lon": -79.973556}, {"type": "node", "id": 155990384, "lat": 38.724326, "lon": -79.973541}, {"type": "node", "id": 155990385, "lat": 38.724573, "lon": -79.973499}, {"type": "node", "id": 155990386, "lat": 38.725022, "lon": -79.973485}, {"type": "node", "id": 155990388, "lat": 38.725379, "lon": -79.973444}, {"type": "node", "id": 155990390, "lat": 38.725809, "lon": -79.973343}, {"type": "node", "id": 155990394, "lat": 38.726982, "lon": -79.972597}, {"type": "node", "id": 155990396, "lat": 38.727957, "lon": -79.972034}, {"type": "node", "id": 155990398, "lat": 38.728764, "lon": -79.971605}, {"type": "node", "id": 155990400, "lat": 38.734332, "lon": -79.9694709}, {"type": "node", "id": 155990404, "lat": 38.73483, "lon": -79.969086}, {"type": "node", "id": 155990406, "lat": 38.736135, "lon": -79.967841}, {"type": "node", "id": 155990408, "lat": 38.740507, "lon": -79.965271}, {"type": "node", "id": 155990410, "lat": 38.74088, "lon": -79.965148}, {"type": "node", "id": 155990412, "lat": 38.741717, "lon": -79.96498}, {"type": "node", "id": 155990415, "lat": 38.744842, "lon": -79.963815}, {"type": "node", "id": 155990417, "lat": 38.746295, "lon": -79.962762}, {"type": "node", "id": 155990419, "lat": 38.7478, "lon": -79.961958}, {"type": "node", "id": 155990421, "lat": 38.748773, "lon": -79.960897}, {"type": "node", "id": 155990424, "lat": 38.749298, "lon": -79.959436}, {"type": "node", "id": 155990426, "lat": 38.749441, "lon": -79.959176}, {"type": "node", "id": 155990428, "lat": 38.749647, "lon": -79.958978}, {"type": "node", "id": 155990430, "lat": 38.750198, "lon": -79.958702}, {"type": "node", "id": 155990432, "lat": 38.75185, "lon": -79.958183}, {"type": "node", "id": 155990434, "lat": 38.752251, "lon": -79.957996}, {"type": "node", "id": 155990436, "lat": 38.753749, "lon": -79.957113}, {"type": "node", "id": 155990438, "lat": 38.755848, "lon": -79.955845}, {"type": "node", "id": 155990440, "lat": 38.756866, "lon": -79.95516}, {"type": "node", "id": 155990442, "lat": 38.757343, "lon": -79.954641}, {"type": "node", "id": 155990443, "lat": 38.757906, "lon": -79.954156}, {"type": "node", "id": 155990444, "lat": 38.758943, "lon": -79.953553}, {"type": "node", "id": 155990446, "lat": 38.759611, "lon": -79.953001}, {"type": "node", "id": 155990448, "lat": 38.760023, "lon": -79.952619}, {"type": "node", "id": 155990450, "lat": 38.760361, "lon": -79.95219}, {"type": "node", "id": 155990452, "lat": 38.760712, "lon": -79.951543}, {"type": "node", "id": 155990455, "lat": 38.7610029, "lon": -79.9510697}, {"type": "node", "id": 155990459, "lat": 38.762174, "lon": -79.95019}, {"type": "node", "id": 155990463, "lat": 38.764253, "lon": -79.949236}, {"type": "node", "id": 155990466, "lat": 38.764658, "lon": -79.949063}, {"type": "node", "id": 155990468, "lat": 38.765304, "lon": -79.948563}, {"type": "node", "id": 155990470, "lat": 38.766167, "lon": -79.947785}, {"type": "node", "id": 155990472, "lat": 38.767082, "lon": -79.94689}, {"type": "node", "id": 155990474, "lat": 38.767715, "lon": -79.946158}, {"type": "node", "id": 155990476, "lat": 38.770268, "lon": -79.942457}, {"type": "node", "id": 155990478, "lat": 38.771072, "lon": -79.941116}, {"type": "node", "id": 155990480, "lat": 38.771443, "lon": -79.940255}, {"type": "node", "id": 155990482, "lat": 38.771673, "lon": -79.938932}, {"type": "node", "id": 155990493, "lat": 38.7717537, "lon": -79.9260579}, {"type": "node", "id": 155990495, "lat": 38.7719117, "lon": -79.9241411}, {"type": "node", "id": 155990497, "lat": 38.7721097, "lon": -79.9237103}, {"type": "node", "id": 155990499, "lat": 38.7725474, "lon": -79.9231603}, {"type": "node", "id": 155990501, "lat": 38.7726944, "lon": -79.9229473}, {"type": "node", "id": 155990503, "lat": 38.7732167, "lon": -79.9220262}, {"type": "node", "id": 155990505, "lat": 38.7734372, "lon": -79.9216219}, {"type": "node", "id": 155990507, "lat": 38.7735802, "lon": -79.9213958}, {"type": "node", "id": 155991007, "lat": 38.7752291, "lon": -79.9204086}, {"type": "node", "id": 155991009, "lat": 38.7760104, "lon": -79.9198944}, {"type": "node", "id": 155991011, "lat": 38.7772718, "lon": -79.9184327}, {"type": "node", "id": 155991013, "lat": 38.7784351, "lon": -79.9169355}, {"type": "node", "id": 155991015, "lat": 38.7789087, "lon": -79.9157232}, {"type": "node", "id": 155991017, "lat": 38.7794563, "lon": -79.9147507}, {"type": "node", "id": 155991019, "lat": 38.7798314, "lon": -79.9143426}, {"type": "node", "id": 155991021, "lat": 38.780191, "lon": -79.914134}, {"type": "node", "id": 155991024, "lat": 38.7810533, "lon": -79.9130237}, {"type": "node", "id": 155991027, "lat": 38.781518, "lon": -79.911999}, {"type": "node", "id": 155991029, "lat": 38.782845, "lon": -79.911238}, {"type": "node", "id": 155991031, "lat": 38.7830671, "lon": -79.9110126}, {"type": "node", "id": 155991033, "lat": 38.7832841, "lon": -79.9105862}, {"type": "node", "id": 155991035, "lat": 38.7833407, "lon": -79.9102429}, {"type": "node", "id": 155991037, "lat": 38.7834117, "lon": -79.9090602}, {"type": "node", "id": 155991039, "lat": 38.7835813, "lon": -79.9084929}, {"type": "node", "id": 155991041, "lat": 38.7841801, "lon": -79.9076455}, {"type": "node", "id": 155991043, "lat": 38.7847431, "lon": -79.9071246}, {"type": "node", "id": 155991045, "lat": 38.7850423, "lon": -79.9068685}, {"type": "node", "id": 155991047, "lat": 38.7867108, "lon": -79.906748}, {"type": "node", "id": 155991049, "lat": 38.7898565, "lon": -79.9052593}, {"type": "node", "id": 155991051, "lat": 38.7907429, "lon": -79.9044895}, {"type": "node", "id": 155991053, "lat": 38.791561, "lon": -79.903822}, {"type": "node", "id": 155991055, "lat": 38.792021, "lon": -79.903514}, {"type": "node", "id": 155991057, "lat": 38.7936428, "lon": -79.9031247}, {"type": "node", "id": 155991059, "lat": 38.7945115, "lon": -79.9027714}, {"type": "node", "id": 155991061, "lat": 38.7946945, "lon": -79.9026107}, {"type": "node", "id": 155991063, "lat": 38.7949376, "lon": -79.9022846}, {"type": "node", "id": 155991065, "lat": 38.7955305, "lon": -79.9013532}, {"type": "node", "id": 155991067, "lat": 38.7968119, "lon": -79.8991786}, {"type": "node", "id": 155991068, "lat": 38.7972166, "lon": -79.8985896}, {"type": "node", "id": 2206880185, "lat": 38.7094644, "lon": -79.9786179}, {"type": "node", "id": 2206880188, "lat": 38.7098674, "lon": -79.9787372}, {"type": "node", "id": 2640577204, "lat": 38.7334401, "lon": -79.9696427}, {"type": "node", "id": 2640577223, "lat": 38.7319315, "lon": -79.9697708}, {"type": "node", "id": 2640577225, "lat": 38.733955, "lon": -79.969589}, {"type": "node", "id": 2640577314, "lat": 38.7302902, "lon": -79.9707135}, {"type": "node", "id": 2640577319, "lat": 38.7317144, "lon": -79.9698613}, {"type": "node", "id": 2640577329, "lat": 38.726388, "lon": -79.973016}, {"type": "node", "id": 2640577345, "lat": 38.72734, "lon": -79.972412}, {"type": "node", "id": 2642979023, "lat": 38.720893, "lon": -79.974243}, {"type": "node", "id": 2642979028, "lat": 38.7218489, "lon": -79.9737973}, {"type": "node", "id": 2642979038, "lat": 38.72286, "lon": -79.973713}, {"type": "node", "id": 2642979042, "lat": 38.72303, "lon": -79.97371}, {"type": "node", "id": 2806158349, "lat": 38.6588548, "lon": -79.9336436}, {"type": "node", "id": 2806158350, "lat": 38.6587326, "lon": -79.9333454}, {"type": "node", "id": 2806158351, "lat": 38.658683, "lon": -79.9330668}, {"type": "node", "id": 2806158352, "lat": 38.6586601, "lon": -79.9327783}, {"type": "node", "id": 2806158353, "lat": 38.6587555, "lon": -79.9310625}, {"type": "node", "id": 2806158354, "lat": 38.6589349, "lon": -79.9304025}, {"type": "node", "id": 2806158355, "lat": 38.6593587, "lon": -79.929767}, {"type": "node", "id": 2806158356, "lat": 38.6596984, "lon": -79.9294834}, {"type": "node", "id": 2806158357, "lat": 38.6644967, "lon": -79.9277626}, {"type": "node", "id": 2806158358, "lat": 38.6646035, "lon": -79.9276355}, {"type": "node", "id": 2806158359, "lat": 38.6646608, "lon": -79.9275182}, {"type": "node", "id": 2806158360, "lat": 38.6646951, "lon": -79.9273862}, {"type": "node", "id": 2806158361, "lat": 38.6645119, "lon": -79.9268485}, {"type": "node", "id": 2806158362, "lat": 38.6642867, "lon": -79.9267458}, {"type": "node", "id": 2806158363, "lat": 38.6639508, "lon": -79.9267947}, {"type": "node", "id": 2806158364, "lat": 38.6625041, "lon": -79.92722}, {"type": "node", "id": 2806158365, "lat": 38.6623743, "lon": -79.9271956}, {"type": "node", "id": 2806158366, "lat": 38.6620995, "lon": -79.9270342}, {"type": "node", "id": 2806158367, "lat": 38.6619964, "lon": -79.9268876}, {"type": "node", "id": 2806158368, "lat": 38.661859, "lon": -79.92656}, {"type": "node", "id": 2806158369, "lat": 38.6618361, "lon": -79.9263743}, {"type": "node", "id": 2806158370, "lat": 38.6618666, "lon": -79.9249615}, {"type": "node", "id": 2806158371, "lat": 38.661817, "lon": -79.9244286}, {"type": "node", "id": 2806158372, "lat": 38.6617597, "lon": -79.9241842}, {"type": "node", "id": 2806158373, "lat": 38.6616872, "lon": -79.9239398}, {"type": "node", "id": 2806158374, "lat": 38.6616032, "lon": -79.9237149}, {"type": "node", "id": 2806158375, "lat": 38.6614849, "lon": -79.92349}, {"type": "node", "id": 2806158376, "lat": 38.6603741, "lon": -79.9217643}, {"type": "node", "id": 2806158377, "lat": 38.6602557, "lon": -79.9217057}, {"type": "node", "id": 2806158378, "lat": 38.6600229, "lon": -79.921691}, {"type": "node", "id": 2806158379, "lat": 38.6598931, "lon": -79.921735}, {"type": "node", "id": 2806158380, "lat": 38.6597938, "lon": -79.9218034}, {"type": "node", "id": 2806158381, "lat": 38.6596946, "lon": -79.9219501}, {"type": "node", "id": 2806158382, "lat": 38.6596488, "lon": -79.9234607}, {"type": "node", "id": 2806158383, "lat": 38.6596182, "lon": -79.9237344}, {"type": "node", "id": 2806158384, "lat": 38.6595572, "lon": -79.9239153}, {"type": "node", "id": 2806158385, "lat": 38.6592136, "lon": -79.9242184}, {"type": "node", "id": 2806158386, "lat": 38.6590953, "lon": -79.9242477}, {"type": "node", "id": 2806158387, "lat": 38.6588624, "lon": -79.9242037}, {"type": "node", "id": 2806158388, "lat": 38.6587593, "lon": -79.9241597}, {"type": "node", "id": 2806158389, "lat": 38.6554077, "lon": -79.920997}, {"type": "node", "id": 2806158390, "lat": 38.6552503, "lon": -79.9209036}, {"type": "node", "id": 2806158391, "lat": 38.6551197, "lon": -79.9208741}, {"type": "node", "id": 2806158392, "lat": 38.6548587, "lon": -79.9209085}, {"type": "node", "id": 2806158393, "lat": 38.6547128, "lon": -79.9209626}, {"type": "node", "id": 2806158394, "lat": 38.6544288, "lon": -79.9213362}, {"type": "node", "id": 2806158395, "lat": 38.6537608, "lon": -79.9228945}, {"type": "node", "id": 2806158396, "lat": 38.6534805, "lon": -79.9231894}, {"type": "node", "id": 2806158397, "lat": 38.6531504, "lon": -79.9233959}, {"type": "node", "id": 2806158398, "lat": 38.6529738, "lon": -79.9234254}, {"type": "node", "id": 2806158399, "lat": 38.6526014, "lon": -79.923386}, {"type": "node", "id": 2806158400, "lat": 38.6524363, "lon": -79.9233369}, {"type": "node", "id": 2806158501, "lat": 38.6522981, "lon": -79.9232582}, {"type": "node", "id": 2806158502, "lat": 38.6522022, "lon": -79.9231599}, {"type": "node", "id": 2902769302, "lat": 38.7718368, "lon": -79.9247153}, {"type": "node", "id": 2902769303, "lat": 38.7718591, "lon": -79.9244538}, {"type": "node", "id": 2902769304, "lat": 38.7719643, "lon": -79.9239879}, {"type": "node", "id": 2902769305, "lat": 38.7720152, "lon": -79.9238775}, {"type": "node", "id": 2902769306, "lat": 38.7721762, "lon": -79.9236078}, {"type": "node", "id": 2902769307, "lat": 38.7723594, "lon": -79.9233953}, {"type": "node", "id": 2906009858, "lat": 38.7942554, "lon": -79.902926}, {"type": "node", "id": 2906009859, "lat": 38.7952306, "lon": -79.9018537}, {"type": "node", "id": 4103702762, "lat": 38.7892983, "lon": -79.9055651}, {"type": "node", "id": 4103702766, "lat": 38.7901241, "lon": -79.9050823}, {"type": "node", "id": 4358012226, "lat": 38.773733, "lon": -79.9211924}, {"type": "node", "id": 4419193436, "lat": 38.795366, "lon": -79.9016278}, {"type": "node", "id": 4419193437, "lat": 38.7956995, "lon": -79.9010594}, {"type": "node", "id": 4419193442, "lat": 38.7959675, "lon": -79.9005937}, {"type": "node", "id": 4734087066, "lat": 38.7778122, "lon": -79.9177527}, {"type": "node", "id": 4734087067, "lat": 38.7781574, "lon": -79.9173673}, {"type": "node", "id": 4734087068, "lat": 38.778277, "lon": -79.9172086}, {"type": "node", "id": 4734087069, "lat": 38.7787058, "lon": -79.9162614}, {"type": "node", "id": 4734087070, "lat": 38.779173, "lon": -79.9152274}, {"type": "node", "id": 4734087071, "lat": 38.7792956, "lon": -79.9150067}, {"type": "node", "id": 4734087072, "lat": 38.7796343, "lon": -79.9145385}, {"type": "node", "id": 4734087073, "lat": 38.7763673, "lon": -79.919608}, {"type": "node", "id": 4734087078, "lat": 38.7720484, "lon": -79.928869}, {"type": "node", "id": 4734087080, "lat": 38.7717715, "lon": -79.9265959}, {"type": "node", "id": 4734087081, "lat": 38.7718703, "lon": -79.9270808}, {"type": "node", "id": 4734087082, "lat": 38.7720097, "lon": -79.927671}, {"type": "node", "id": 4734087083, "lat": 38.7720544, "lon": -79.9279407}, {"type": "node", "id": 4734093229, "lat": 38.7720046, "lon": -79.9320273}, {"type": "node", "id": 5076779227, "lat": 38.6640252, "lon": -79.9382535}, {"type": "node", "id": 5076779228, "lat": 38.6642629, "lon": -79.938405}, {"type": "node", "id": 5076779229, "lat": 38.6649404, "lon": -79.9389535}, {"type": "node", "id": 5076779230, "lat": 38.6651422, "lon": -79.9391607}, {"type": "node", "id": 5076779288, "lat": 38.6759673, "lon": -79.9533401}, {"type": "node", "id": 5076779289, "lat": 38.6759135, "lon": -79.9530349}, {"type": "node", "id": 5076779290, "lat": 38.6758413, "lon": -79.9527179}, {"type": "node", "id": 5076779291, "lat": 38.6757666, "lon": -79.9524501}, {"type": "node", "id": 5076779292, "lat": 38.6756807, "lon": -79.9521693}, {"type": "node", "id": 5076779293, "lat": 38.6747364, "lon": -79.9505204}, {"type": "node", "id": 5076779294, "lat": 38.6749487, "lon": -79.9507976}, {"type": "node", "id": 5076779295, "lat": 38.6752426, "lon": -79.9512367}, {"type": "node", "id": 5076779296, "lat": 38.6769858, "lon": -79.9592042}, {"type": "node", "id": 5076779297, "lat": 38.6770696, "lon": -79.9595609}, {"type": "node", "id": 5076779298, "lat": 38.677286, "lon": -79.9602886}, {"type": "node", "id": 5076779328, "lat": 38.6817839, "lon": -79.9722344}, {"type": "node", "id": 5076779329, "lat": 38.6815034, "lon": -79.9717663}, {"type": "node", "id": 5076779330, "lat": 38.681383, "lon": -79.9715249}, {"type": "node", "id": 5076779331, "lat": 38.6812542, "lon": -79.9712192}, {"type": "node", "id": 5077083814, "lat": 38.7130526, "lon": -79.9793883}, {"type": "node", "id": 5077083817, "lat": 38.716193, "lon": -79.978148}, {"type": "node", "id": 5077083818, "lat": 38.715855, "lon": -79.978416}, {"type": "node", "id": 5077083819, "lat": 38.714235, "lon": -79.979312}, {"type": "node", "id": 5077084829, "lat": 38.7105177, "lon": -79.9788944}, {"type": "node", "id": 5077084831, "lat": 38.7102764, "lon": -79.9788256}, {"type": "node", "id": 5077084832, "lat": 38.7100848, "lon": -79.9787831}, {"type": "node", "id": 5077084834, "lat": 38.7090055, "lon": -79.9784872}, {"type": "node", "id": 5077084835, "lat": 38.7088271, "lon": -79.9784334}, {"type": "node", "id": 5077084836, "lat": 38.7084443, "lon": -79.9783223}, {"type": "node", "id": 5077086155, "lat": 38.687538, "lon": -79.9740241}, {"type": "node", "id": 5443107289, "lat": 38.7296425, "lon": -79.9711213}, {"type": "node", "id": 5443126091, "lat": 38.75281, "lon": -79.957698}, {"type": "node", "id": 5443126092, "lat": 38.753086, "lon": -79.957508}, {"type": "node", "id": 5443126093, "lat": 38.754475, "lon": -79.956825}, {"type": "node", "id": 5443126094, "lat": 38.754901, "lon": -79.956625}, {"type": "node", "id": 5443126095, "lat": 38.755104, "lon": -79.956506}, {"type": "node", "id": 5443126096, "lat": 38.755259, "lon": -79.956396}, {"type": "node", "id": 5443126097, "lat": 38.756173, "lon": -79.955607}, {"type": "node", "id": 5443126098, "lat": 38.756744, "lon": -79.955256}, {"type": "node", "id": 5443126099, "lat": 38.75765, "lon": -79.954345}, {"type": "node", "id": 5443126100, "lat": 38.759128, "lon": -79.953415}, {"type": "node", "id": 5443126101, "lat": 38.7602, "lon": -79.952414}, {"type": "node", "id": 5443126102, "lat": 38.760537, "lon": -79.951889}, {"type": "node", "id": 5443126103, "lat": 38.7608467, "lon": -79.9512881}, {"type": "node", "id": 5443126104, "lat": 38.761219, "lon": -79.9508112}, {"type": "node", "id": 5443126105, "lat": 38.761434, "lon": -79.9506211}, {"type": "node", "id": 5443126108, "lat": 38.761787, "lon": -79.950389}, {"type": "node", "id": 5443126111, "lat": 38.763325, "lon": -79.949575}, {"type": "node", "id": 5443126112, "lat": 38.763535, "lon": -79.949483}, {"type": "node", "id": 5443126113, "lat": 38.767464, "lon": -79.946478}, {"type": "node", "id": 5443126114, "lat": 38.767964, "lon": -79.945785}, {"type": "node", "id": 5443126115, "lat": 38.768293, "lon": -79.9452}, {"type": "node", "id": 5443126116, "lat": 38.768546, "lon": -79.944802}, {"type": "node", "id": 5443126117, "lat": 38.769599, "lon": -79.943454}, {"type": "node", "id": 5443126118, "lat": 38.769978, "lon": -79.94286}, {"type": "node", "id": 5443126119, "lat": 38.770684, "lon": -79.941719}, {"type": "node", "id": 5443126120, "lat": 38.771194, "lon": -79.94097}, {"type": "node", "id": 5443126121, "lat": 38.771266, "lon": -79.940815}, {"type": "node", "id": 5443126122, "lat": 38.771533, "lon": -79.939818}, {"type": "node", "id": 5443126123, "lat": 38.771743, "lon": -79.938211}, {"type": "node", "id": 5443126124, "lat": 38.771766, "lon": -79.937031}, {"type": "node", "id": 5443126125, "lat": 38.771779, "lon": -79.936826}, {"type": "node", "id": 5443126126, "lat": 38.771833, "lon": -79.9364}, {"type": "node", "id": 5443126127, "lat": 38.771917, "lon": -79.936057}, {"type": "node", "id": 5443126128, "lat": 38.771926, "lon": -79.935914}, {"type": "node", "id": 5443126129, "lat": 38.77206, "lon": -79.935021}, {"type": "node", "id": 5443126130, "lat": 38.772068, "lon": -79.934399}, {"type": "node", "id": 5443126131, "lat": 38.712235, "lon": -79.979251}, {"type": "node", "id": 5443126132, "lat": 38.7289542, "lon": -79.9715035}, {"type": "node", "id": 5443126133, "lat": 38.7290674, "lon": -79.971441}, {"type": "node", "id": 5443126134, "lat": 38.7292972, "lon": -79.9713113}, {"type": "node", "id": 5443126135, "lat": 38.7313516, "lon": -79.9700617}, {"type": "node", "id": 5443126136, "lat": 38.7314605, "lon": -79.9699961}, {"type": "node", "id": 5443126137, "lat": 38.7315549, "lon": -79.9699452}, {"type": "node", "id": 5443126138, "lat": 38.732052, "lon": -79.9697396}, {"type": "node", "id": 5443126139, "lat": 38.732479, "lon": -79.969674}, {"type": "node", "id": 5443126140, "lat": 38.734607, "lon": -79.96927}, {"type": "node", "id": 5443126141, "lat": 38.736564, "lon": -79.967477}, {"type": "node", "id": 5443126142, "lat": 38.737431, "lon": -79.966975}, {"type": "node", "id": 5443126143, "lat": 38.738628, "lon": -79.966353}, {"type": "node", "id": 5443126144, "lat": 38.740217, "lon": -79.965424}, {"type": "node", "id": 5443126145, "lat": 38.742091, "lon": -79.964878}, {"type": "node", "id": 5443126146, "lat": 38.744069, "lon": -79.96419}, {"type": "node", "id": 5443126147, "lat": 38.744414, "lon": -79.964054}, {"type": "node", "id": 5443126148, "lat": 38.745767, "lon": -79.963102}, {"type": "node", "id": 5443126149, "lat": 38.74683, "lon": -79.962458}, {"type": "node", "id": 5443126150, "lat": 38.748153, "lon": -79.961653}, {"type": "node", "id": 5443126151, "lat": 38.748399, "lon": -79.961386}, {"type": "node", "id": 5443126152, "lat": 38.748537, "lon": -79.961223}, {"type": "node", "id": 5443126153, "lat": 38.748984, "lon": -79.960423}, {"type": "node", "id": 5443126154, "lat": 38.749869, "lon": -79.958837}, {"type": "node", "id": 5812105919, "lat": 38.71639, "lon": -79.9779547}, {"type": "node", "id": 5812105921, "lat": 38.7146974, "lon": -79.9790808}, {"type": "node", "id": 5812105923, "lat": 38.7141068, "lon": -79.9793495}, {"type": "node", "id": 5812105924, "lat": 38.7171454, "lon": -79.9771516}, {"type": "node", "id": 5812105925, "lat": 38.7193512, "lon": -79.9753802}, {"type": "node", "id": 5812105926, "lat": 38.7191221, "lon": -79.9755436}, {"type": "node", "id": 5812105927, "lat": 38.7166814, "lon": -79.977641}, {"type": "node", "id": 5829261048, "lat": 38.7178693, "lon": -79.9765143}, {"type": "node", "id": 7117231217, "lat": 38.7679291, "lon": -79.9458373}, {"type": "node", "id": 7117307421, "lat": 38.7616105, "lon": -79.9504892}, {"type": "node", "id": 7117307422, "lat": 38.7631053, "lon": -79.9496841}, {"type": "node", "id": 7230784748, "lat": 38.7133981, "lon": -79.9794542}, {"type": "node", "id": 7230784749, "lat": 38.7137586, "lon": -79.9794623}, {"type": "node", "id": 7300659878, "lat": 38.7070308, "lon": -79.9779115}, {"type": "node", "id": 7300659879, "lat": 38.7064902, "lon": -79.977762}, {"type": "node", "id": 7300659880, "lat": 38.7052899, "lon": -79.9774385}, {"type": "node", "id": 7300659881, "lat": 38.7040953, "lon": -79.9771097}, {"type": "node", "id": 7300659882, "lat": 38.7033261, "lon": -79.9768987}, {"type": "node", "id": 7300659883, "lat": 38.7021548, "lon": -79.976581}, {"type": "node", "id": 7300659884, "lat": 38.70004, "lon": -79.976}, {"type": "node", "id": 7300661885, "lat": 38.6986219, "lon": -79.9756193}, {"type": "node", "id": 7300661886, "lat": 38.6970798, "lon": -79.975196}, {"type": "node", "id": 7300661887, "lat": 38.6951857, "lon": -79.9746789}, {"type": "node", "id": 7300661888, "lat": 38.6942777, "lon": -79.9744297}, {"type": "node", "id": 7300661889, "lat": 38.6937021, "lon": -79.9742769}, {"type": "node", "id": 7300661890, "lat": 38.6935215, "lon": -79.9742343}, {"type": "node", "id": 7300661891, "lat": 38.6932195, "lon": -79.9741854}, {"type": "node", "id": 7300661892, "lat": 38.692938, "lon": -79.9741516}, {"type": "node", "id": 7300661893, "lat": 38.6926985, "lon": -79.9741328}, {"type": "node", "id": 7300661894, "lat": 38.6923613, "lon": -79.9741153}, {"type": "node", "id": 7300661895, "lat": 38.6917769, "lon": -79.9741053}, {"type": "node", "id": 7300661896, "lat": 38.6911142, "lon": -79.9740953}, {"type": "node", "id": 7300661897, "lat": 38.6907516, "lon": -79.9740853}, {"type": "node", "id": 7300661898, "lat": 38.6891379, "lon": -79.9740602}, {"type": "node", "id": 7576829541, "lat": 38.6869392, "lon": -79.9740106}, {"type": "node", "id": 7576829542, "lat": 38.6857855, "lon": -79.9739754}, {"type": "node", "id": 7576829543, "lat": 38.685578, "lon": -79.9739716}, {"type": "node", "id": 7576829544, "lat": 38.6854398, "lon": -79.9739703}, {"type": "node", "id": 7576829545, "lat": 38.6849561, "lon": -79.9739684}, {"type": "node", "id": 7576829546, "lat": 38.6847629, "lon": -79.973967}, {"type": "node", "id": 7576829547, "lat": 38.6844834, "lon": -79.9739573}, {"type": "node", "id": 7576829548, "lat": 38.6843602, "lon": -79.9739462}, {"type": "node", "id": 7576829549, "lat": 38.6842457, "lon": -79.9739318}, {"type": "node", "id": 7576829550, "lat": 38.6841473, "lon": -79.9739159}, {"type": "node", "id": 7576829551, "lat": 38.6840565, "lon": -79.9738967}, {"type": "node", "id": 7576829552, "lat": 38.6839071, "lon": -79.9738553}, {"type": "node", "id": 7576829553, "lat": 38.6837727, "lon": -79.9738074}, {"type": "node", "id": 7576829554, "lat": 38.683618, "lon": -79.9737526}, {"type": "node", "id": 7576829555, "lat": 38.683485, "lon": -79.9736989}, {"type": "node", "id": 7576829556, "lat": 38.6833542, "lon": -79.9736378}, {"type": "node", "id": 7576829557, "lat": 38.6832372, "lon": -79.9735804}, {"type": "node", "id": 7576829558, "lat": 38.6831229, "lon": -79.9735167}, {"type": "node", "id": 7576829559, "lat": 38.6830055, "lon": -79.973445}, {"type": "node", "id": 7576829560, "lat": 38.6828693, "lon": -79.9733578}, {"type": "node", "id": 7576829561, "lat": 38.68273, "lon": -79.973259}, {"type": "node", "id": 7576829562, "lat": 38.6825994, "lon": -79.9731562}, {"type": "node", "id": 7576829563, "lat": 38.6824819, "lon": -79.9730527}, {"type": "node", "id": 8413502047, "lat": 38.7879821, "lon": -79.9062559}, {"type": "node", "id": 8413502048, "lat": 38.7870106, "lon": -79.9067223}, {"type": "node", "id": 11072260379, "lat": 38.7742387, "lon": -79.9208441}, {"type": "node", "id": 11072260380, "lat": 38.7747771, "lon": -79.9206}, {"type": "node", "id": 11072260381, "lat": 38.7756547, "lon": -79.9201515}, {"type": "node", "id": 11072260382, "lat": 38.776193, "lon": -79.9197538}, {"type": "node", "id": 11072260383, "lat": 38.7765933, "lon": -79.9193422}, {"type": "node", "id": 12787651785, "lat": 38.7804264, "lon": -79.9139419}, {"type": "node", "id": 12787651786, "lat": 38.781696, "lon": -79.9118016}, {"type": "node", "id": 12787651787, "lat": 38.7819246, "lon": -79.9116275}, {"type": "node", "id": 12787651788, "lat": 38.7821377, "lon": -79.9115061}, {"type": "node", "id": 12787651789, "lat": 38.783184, "lon": -79.9108198}, {"type": "node", "id": 12787651790, "lat": 38.7834867, "lon": -79.908714}, {"type": "node", "id": 12787651791, "lat": 38.783813, "lon": -79.908135}, {"type": "node", "id": 12787651792, "lat": 38.7855244, "lon": -79.906674}, {"type": "node", "id": 12787651793, "lat": 38.7852714, "lon": -79.906755}, {"type": "node", "id": 12787651794, "lat": 38.7858568, "lon": -79.9066308}, {"type": "node", "id": 13184101302, "lat": 38.7340131, "lon": -79.9695768}, {"type": "node", "id": 13184101303, "lat": 38.7341476, "lon": -79.9695362}, {"type": "way", "id": 15643586, "nodes": [155976480, 5443126131, 155966963, 5077083814, 7230784748, 7230784749, 5812105923, 5077083819, 5812105921, 155990366, 5077083818, 5077083817, 5812105919, 155953484, 5812105927, 155911269, 5812105924, 155990370, 5829261048, 5812105926, 155990372, 5812105925, 155959444, 2642979023, 155990374, 155990376, 2642979028, 155990378, 155944107, 155990380, 2642979038, 2642979042, 155990382, 155990384, 155990385, 155990386, 155990388, 155990390, 155978452, 2640577329, 155990394, 2640577345, 155990396, 155990398, 155973068, 5443126132, 5443126133, 5443126134, 5443107289, 2640577314, 155962519, 155975060, 5443126135, 5443126136, 5443126137, 155914857, 2640577319, 2640577223, 5443126138, 155978186, 5443126139, 155971229, 2640577204, 155926098, 2640577225, 13184101302], "tags": {"NHS": "yes", "highway": "trunk", "lanes": "2", "ref": "US 219;US 250;WV 55;WV 92", "tiger:cfcc": "A21", "tiger:county": "Randolph, WV", "tiger:name_base": "P:United States Route 219", "tiger:name_base_1": "State Route 55:United States Route 250", "tiger:name_base_2": "State Route 92", "tiger:name_base_3": "State Route 55:United States Route 250", "tiger:name_base_4": "United States Route 219", "tiger:reviewed": "no"}}, {"type": "way", "id": 210611389, "nodes": [155976476, 2206880185], "tags": {"highway": "trunk", "lanes": "2", "ref": "US 250;WV 92", "tiger:cfcc": "A21", "tiger:county": "Pocahontas, WV:Randolph, WV", "tiger:name_base": "United States Route 250", "tiger:name_base_1": "State Route 92", "tiger:reviewed": "no"}}, {"type": "way", "id": 210611391, "nodes": [2206880188, 5077084832, 5077084831, 5077084829, 155976480], "tags": {"highway": "trunk", "lanes": "2", "ref": "US 250;WV 92", "tiger:cfcc": "A21", "tiger:county": "Pocahontas, WV:Randolph, WV", "tiger:name_base": "United States Route 250", "tiger:name_base_1": "State Route 92", "tiger:reviewed": "no"}}, {"type": "way", "id": 210611392, "nodes": [2206880185, 2206880188], "tags": {"bridge": "yes", "highway": "trunk", "lanes": "2", "layer": "1", "ref": "US 250;WV 92", "source": "Bing", "tiger:cfcc": "A21", "tiger:county": "Pocahontas, WV:Randolph, WV", "tiger:name_base": "United States Route 250", "tiger:name_base_1": "State Route 92"}}, {"type": "way", "id": 565081450, "nodes": [155917085, 155990432, 155990434, 5443126091, 5443126092, 155990436, 5443126093, 5443126094, 5443126095, 5443126096, 155990438, 5443126097, 5443126098, 155990440, 155990442, 5443126099, 155990443, 155990444, 5443126100, 155922465, 155990446, 155990448, 5443126101, 155990450, 5443126102, 155990452, 5443126103, 155990455, 5443126104, 5443126105, 7117307421, 5443126108, 155990459, 7117307422, 5443126111, 5443126112, 155990463, 155990466, 155990468, 155990470, 155950348, 155990472, 5443126113, 155990474, 155980907, 7117231217, 5443126114, 5443126115, 5443126116, 5443126117, 5443126118, 155990476, 5443126119, 155990478, 5443126120, 5443126121, 155990480, 5443126122, 155990482, 5443126123, 155930407, 5443126124, 5443126125, 5443126126, 5443126127, 5443126128, 5443126129, 5443126130, 155946641], "tags": {"NHS": "yes", "highway": "trunk", "lanes": "2", "ref": "US 219;US 250;WV 55;WV 92", "tiger:cfcc": "A21", "tiger:county": "Randolph, WV", "tiger:name_base": "P:United States Route 219", "tiger:name_base_1": "State Route 55:United States Route 250", "tiger:name_base_2": "State Route 92", "tiger:name_base_3": "State Route 55:United States Route 250", "tiger:name_base_4": "United States Route 219", "tiger:reviewed": "no"}}, {"type": "way", "id": 565081451, "nodes": [155946641, 155946655, 4734093229, 155916508, 155982295, 4734087078, 155930442, 4734087083, 4734087082, 4734087081, 4734087080, 155990493, 155975976, 2902769302, 2902769303, 155990495, 2902769304, 2902769305, 155990497, 2902769306, 2902769307, 155990499, 155990501, 155988336, 155990503, 155990505, 155990507, 4358012226, 155985461, 11072260379, 11072260380, 155991007, 11072260381, 155991009, 11072260382, 4734087073, 11072260383, 155991011, 4734087066, 4734087067, 4734087068, 155991013, 4734087069, 155991015, 4734087070, 4734087071, 155991017, 4734087072, 155991019, 155991021, 12787651785, 155936538, 155991024, 155991027, 12787651786, 12787651787, 12787651788, 155991029, 155991031, 12787651789, 155991033, 155991035, 155988204, 155991037, 12787651790, 155991039, 12787651791, 155991041, 155915648, 155991043, 155991045, 12787651793, 12787651792, 12787651794, 155954739, 155991047, 8413502048, 8413502047, 4103702762, 155991049, 4103702766, 155991051, 155991053, 155991055, 155991057, 2906009858, 155991059, 155991061, 155991063, 2906009859, 4419193436, 155991065, 4419193437, 4419193442, 155936581, 155991067, 155987402, 155991068], "tags": {"NHS": "yes", "highway": "trunk", "lanes": "2", "ref": "US 219;US 250;WV 55;WV 92", "tiger:cfcc": "A21", "tiger:county": "Randolph, WV", "tiger:name_base": "P:United States Route 219", "tiger:name_base_1": "State Route 55:United States Route 250", "tiger:name_base_2": "State Route 92", "tiger:name_base_3": "State Route 55:United States Route 250", "tiger:name_base_4": "United States Route 219", "tiger:reviewed": "no"}}, {"type": "way", "id": 767364769, "nodes": [155976352, 155976353, 2806158502, 2806158501, 2806158400, 2806158399, 155976354, 2806158398, 2806158397, 155976355, 2806158396, 155976356, 2806158395, 155976358, 2806158394, 155976360, 155976362, 2806158393, 2806158392, 155976365, 2806158391, 2806158390, 2806158389, 155976366, 155976367, 155976369, 2806158388, 2806158387, 155976371, 2806158386, 2806158385, 155976373, 155976375, 2806158384, 2806158383, 2806158382, 155976378, 155976380, 2806158381, 2806158380, 2806158379, 2806158378, 155976382, 2806158377, 2806158376, 155976384, 155976386, 2806158375, 2806158374, 2806158373, 2806158372, 2806158371, 155976388, 2806158370, 155976390, 2806158369, 2806158368, 155976392, 2806158367, 2806158366, 155976394, 2806158365, 2806158364, 155976400, 155976401, 2806158363, 155976402, 2806158362, 155976403, 2806158361, 155976404, 155976406, 155914586, 2806158360, 2806158359, 2806158358, 2806158357, 155976408, 155976410, 155976411, 155976414, 2806158356, 155976416, 2806158355, 155976417, 2806158354, 155976418, 2806158353, 155976420, 2806158352, 2806158351, 2806158350, 2806158349, 155957661, 155976422, 155976424, 155976426, 155950574, 155976428, 155976430, 5076779227, 5076779228, 155976432, 155976434, 5076779229, 5076779230, 155976436, 155928995, 5076779293, 5076779294, 155976448, 5076779295, 155928956, 155976450, 155976451, 5076779292, 5076779291, 5076779290, 5076779289, 5076779288, 155976453, 5076779296, 5076779297, 155976454, 5076779298, 155925689, 155925502, 155976456, 155925485, 5076779331, 5076779330, 5076779329, 155949982, 5076779328, 7576829563], "tags": {"highway": "trunk", "lanes": "2", "maxspeed": "55 mph", "ref": "US 250;WV 92", "tiger:cfcc": "A21", "tiger:county": "Pocahontas, WV:Randolph, WV", "tiger:name_base": "United States Route 250", "tiger:name_base_1": "State Route 92", "tiger:reviewed": "no"}}, {"type": "way", "id": 781947294, "nodes": [7300659878, 5077084836, 5077084835, 5077084834, 155976476], "tags": {"highway": "trunk", "lanes": "2", "maxspeed": "55 mph", "ref": "US 250;WV 92", "tiger:cfcc": "A21", "tiger:county": "Pocahontas, WV:Randolph, WV", "tiger:name_base": "United States Route 250", "tiger:name_base_1": "State Route 92", "tiger:reviewed": "no"}}, {"type": "way", "id": 781947295, "nodes": [7576829563, 7576829562], "tags": {"highway": "trunk", "lanes": "2", "maxspeed": "55 mph", "name": "Staunton & Parkersburg Turnpike", "oneway": "no", "ref": "US 250;WV 92", "surface": "asphalt", "tiger:cfcc": "A21", "tiger:county": "Pocahontas, WV:Randolph, WV", "tiger:name_base": "United States Route 250", "tiger:name_base_1": "State Route 92", "tiger:reviewed": "yes"}}, {"type": "way", "id": 810379983, "nodes": [155924892, 7300661887, 7300661886, 7300661885, 7300659884, 7300659883, 7300659882, 7300659881, 7300659880, 7300659879, 7300659878], "tags": {"highway": "trunk", "lanes": "2", "maxspeed": "55 mph", "name": "Staunton & Parkersburg Turnpike", "oneway": "no", "ref": "US 250;WV 92", "surface": "asphalt", "tiger:cfcc": "A21", "tiger:county": "Pocahontas, WV:Randolph, WV", "tiger:name_base": "United States Route 250", "tiger:name_base_1": "State Route 92", "tiger:reviewed": "yes"}}, {"type": "way", "id": 810386589, "nodes": [7576829562, 7576829561, 7576829560, 7576829559, 7576829558, 7576829557, 7576829556, 7576829555, 7576829554, 7576829553, 7576829552, 7576829551, 7576829550, 7576829549, 7576829548, 7576829547, 155929258, 7576829546, 7576829545, 7576829544, 7576829543, 7576829542, 7576829541, 5077086155, 7300661898, 7300661897, 7300661896, 7300661895, 7300661894, 7300661893, 7300661892, 7300661891, 7300661890, 7300661889, 7300661888, 155924892], "tags": {"highway": "trunk", "lanes": "2", "maxspeed": "55 mph", "name": "Staunton & Parkersburg Turnpike", "oneway": "no", "ref": "US 250;WV 92", "surface": "asphalt", "tiger:cfcc": "A21", "tiger:county": "Pocahontas, WV:Randolph, WV", "tiger:name_base": "United States Route 250", "tiger:name_base_1": "State Route 92", "tiger:reviewed": "yes"}}, {"type": "way", "id": 1434380507, "nodes": [155990400, 5443126140, 155990404, 155990406, 5443126141, 5443126142, 5443126143, 5443126144, 155990408, 155990410, 155990412, 5443126145, 155932662, 5443126146, 5443126147, 155990415, 5443126148, 155990417, 5443126149, 155990419, 5443126150, 5443126151, 5443126152, 155990421, 5443126153, 155990424, 155990426, 155990428, 5443126154, 155990430, 155917085], "tags": {"NHS": "yes", "highway": "trunk", "lanes": "2", "ref": "US 219;US 250;WV 55;WV 92", "tiger:cfcc": "A21", "tiger:county": "Randolph, WV", "tiger:name_base": "P:United States Route 219", "tiger:name_base_1": "State Route 55:United States Route 250", "tiger:name_base_2": "State Route 92", "tiger:name_base_3": "State Route 55:United States Route 250", "tiger:name_base_4": "United States Route 219", "tiger:reviewed": "no"}}, {"type": "way", "id": 1434380508, "nodes": [13184101302, 13184101303, 155990400], "tags": {"NHS": "yes", "bridge": "yes", "highway": "trunk", "lanes": "2", "layer": "1", "ref": "US 219;US 250;WV 55;WV 92", "tiger:cfcc": "A21", "tiger:county": "Randolph, WV", "tiger:name_base": "P:United States Route 219", "tiger:name_base_1": "State Route 55:United States Route 250", "tiger:name_base_2": "State Route 92", "tiger:name_base_3": "State Route 55:United States Route 250", "tiger:name_base_4": "United States Route 219", "tiger:reviewed": "no"}}]}