{"version": 0.6, "generator": "Overpass API 0.7.62.10 2d4cfc48", "osm3s": {"timestamp_osm_base": "2026-01-29T02:12:55Z", "copyright": "The data included in this document is from www.openstreetmap.org. The data is made available under ODbL."}, "elements": [{"type": "node", "id": 66981852, "lat": 30.8326935, "lon": -82.00641, "tags": {"highway": "traffic_signals"}}, {"type": "node", "id": 66996882, "lat": 30.825265, "lon": -82.0042213}, {"type": "node", "id": 67007802, "lat": 30.8393832, "lon": -82.0067602}, {"type": "node", "id": 67008641, "lat": 30.7904108, "lon": -81.9827307}, {"type": "node", "id": 67019727, "lat": 30.8415833, "lon": -82.0065442}, {"type": "node", "id": 67020355, "lat": 30.8193044, "lon": -82.0014277}, {"type": "node", "id": 67022277, "lat": 30.7886469, "lon": -81.9819555}, {"type": "node", "id": 67024388, "lat": 30.8438615, "lon": -82.0071084}, {"type": "node", "id": 67024904, "lat": 30.8225869, "lon": -82.0029225}, {"type": "node", "id": 67031268, "lat": 30.809408, "lon": -81.9969172}, {"type": "node", "id": 67031435, "lat": 30.808039, "lon": -81.9963769}, {"type": "node", "id": 67031783, "lat": 30.8248686, "lon": -82.004064}, {"type": "node", "id": 67033317, "lat": 30.843996, "lon": -82.0069523}, {"type": "node", "id": 67034139, "lat": 30.7989065, "lon": -81.9875093}, {"type": "node", "id": 67034140, "lat": 30.7990175, "lon": -81.987352}, {"type": "node", "id": 67035495, "lat": 30.8056837, "lon": -81.9940533}, {"type": "node", "id": 67036030, "lat": 30.8199025, "lon": -82.0017016}, {"type": "node", "id": 67044868, "lat": 30.7966333, "lon": -81.9855142}, {"type": "node", "id": 67045884, "lat": 30.840258, "lon": -82.006534}, {"type": "node", "id": 67053123, "lat": 30.813118, "lon": -81.9988302}, {"type": "node", "id": 67055591, "lat": 30.8127482, "lon": -81.9984392}, {"type": "node", "id": 67061896, "lat": 30.8234973, "lon": -82.0033736}, {"type": "node", "id": 67066302, "lat": 30.8242268, "lon": -82.0037784}, {"type": "node", "id": 67066306, "lat": 30.8244161, "lon": -82.0038644}, {"type": "node", "id": 67066309, "lat": 30.8266638, "lon": -82.0046551}, {"type": "node", "id": 67066557, "lat": 30.8106163, "lon": -81.9974663}, {"type": "node", "id": 67067471, "lat": 30.8281067, "lon": -82.005097}, {"type": "node", "id": 67068597, "lat": 30.8288636, "lon": -82.0053338}, {"type": "node", "id": 67070350, "lat": 30.8436415, "lon": -82.0070594}, {"type": "node", "id": 67070812, "lat": 30.8337061, "lon": -82.0067178}, {"type": "node", "id": 67071028, "lat": 30.83034, "lon": -82.0057853}, {"type": "node", "id": 67071534, "lat": 30.8296114, "lon": -82.005564, "tags": {"highway": "traffic_signals", "traffic_signals:direction": "both"}}, {"type": "node", "id": 67071538, "lat": 30.8274041, "lon": -82.0048852}, {"type": "node", "id": 67071964, "lat": 30.8207912, "lon": -82.0021046}, {"type": "node", "id": 67071967, "lat": 30.8231428, "lon": -82.0031878}, {"type": "node", "id": 67071974, "lat": 30.8344269, "lon": -82.0069308}, {"type": "node", "id": 67071976, "lat": 30.8348426, "lon": -82.0070423}, {"type": "node", "id": 67071978, "lat": 30.8352743, "lon": -82.0071274}, {"type": "node", "id": 67071980, "lat": 30.8357858, "lon": -82.0071773}, {"type": "node", "id": 67071983, "lat": 30.8362074, "lon": -82.0071802}, {"type": "node", "id": 67071985, "lat": 30.8368676, "lon": -82.0071219}, {"type": "node", "id": 67084867, "lat": 30.7859472, "lon": -81.9807695}, {"type": "node", "id": 67084873, "lat": 30.792072, "lon": -81.9834621}, {"type": "node", "id": 67084879, "lat": 30.7958568, "lon": -81.9851313}, {"type": "node", "id": 67084887, "lat": 30.7962421, "lon": -81.9853114}, {"type": "node", "id": 67084891, "lat": 30.7969589, "lon": -81.9857107}, {"type": "node", "id": 67084897, "lat": 30.797196, "lon": -81.9858604}, {"type": "node", "id": 67084902, "lat": 30.7975283, "lon": -81.986085}, {"type": "node", "id": 67084912, "lat": 30.7980843, "lon": -81.9865046}, {"type": "node", "id": 67084917, "lat": 30.7986282, "lon": -81.9869741}, {"type": "node", "id": 67084922, "lat": 30.7988318, "lon": -81.9871737}, {"type": "node", "id": 67084934, "lat": 30.7998192, "lon": -81.9881563}, {"type": "node", "id": 67084941, "lat": 30.8033587, "lon": -81.9917144}, {"type": "node", "id": 67084948, "lat": 30.8042718, "lon": -81.9926314}, {"type": "node", "id": 67084957, "lat": 30.8065111, "lon": -81.9948757}, {"type": "node", "id": 67084963, "lat": 30.8067205, "lon": -81.995082}, {"type": "node", "id": 67084970, "lat": 30.8069876, "lon": -81.9953301}, {"type": "node", "id": 67084973, "lat": 30.8073703, "lon": -81.9956455}, {"type": "node", "id": 67084978, "lat": 30.8078638, "lon": -81.996015}, {"type": "node", "id": 67084981, "lat": 30.8082389, "lon": -81.9962698}, {"type": "node", "id": 67084983, "lat": 30.8086235, "lon": -81.9965025}, {"type": "node", "id": 67084986, "lat": 30.8100403, "lon": -81.9972042}, {"type": "node", "id": 67084993, "lat": 30.817642, "lon": -82.000671}, {"type": "node", "id": 67085019, "lat": 30.8388014, "lon": -82.0067883}, {"type": "node", "id": 67085022, "lat": 30.8389313, "lon": -82.0068324}, {"type": "node", "id": 67085023, "lat": 30.8394801, "lon": -82.0066087}, {"type": "node", "id": 67085024, "lat": 30.8398032, "lon": -82.0065741}, {"type": "node", "id": 67085025, "lat": 30.8405845, "lon": -82.006529}, {"type": "node", "id": 67085028, "lat": 30.8419657, "lon": -82.0065719}, {"type": "node", "id": 67085031, "lat": 30.8422887, "lon": -82.0066061}, {"type": "node", "id": 67085035, "lat": 30.8426208, "lon": -82.0066507}, {"type": "node", "id": 67085038, "lat": 30.8430958, "lon": -82.0067296}, {"type": "node", "id": 67085042, "lat": 30.8433072, "lon": -82.0067752}, {"type": "node", "id": 67085045, "lat": 30.8443782, "lon": -82.0070725}, {"type": "node", "id": 67085047, "lat": 30.8449945, "lon": -82.0072533}, {"type": "node", "id": 384421823, "lat": 30.8109291, "lon": -81.9974991}, {"type": "node", "id": 663340665, "lat": 30.8383376, "lon": -82.0072876}, {"type": "node", "id": 2055464014, "lat": 30.7849988, "lon": -81.9803501}, {"type": "node", "id": 2237437682, "lat": 30.7849405, "lon": -81.9805459}, {"type": "node", "id": 2237437686, "lat": 30.7856299, "lon": -81.9808473}, {"type": "node", "id": 2237437687, "lat": 30.786131, "lon": -81.9810657}, {"type": "node", "id": 2237437705, "lat": 30.7871169, "lon": -81.9814995}, {"type": "node", "id": 2237437706, "lat": 30.7871665, "lon": -81.981303}, {"type": "node", "id": 2237437707, "lat": 30.7876253, "lon": -81.9817249}, {"type": "node", "id": 2237437708, "lat": 30.7887755, "lon": -81.9822322}, {"type": "node", "id": 2237437710, "lat": 30.7920101, "lon": -81.9836555}, {"type": "node", "id": 2237437712, "lat": 30.7936643, "lon": -81.9843827}, {"type": "node", "id": 2237437714, "lat": 30.7957089, "lon": -81.9852857}, {"type": "node", "id": 2237437716, "lat": 30.7960851, "lon": -81.9854546}, {"type": "node", "id": 2237437717, "lat": 30.7964442, "lon": -81.9856433}, {"type": "node", "id": 2237437718, "lat": 30.796759, "lon": -81.9858196}, {"type": "node", "id": 2237437719, "lat": 30.7971141, "lon": -81.9860364}, {"type": "node", "id": 2237437721, "lat": 30.7974343, "lon": -81.9862454}, {"type": "node", "id": 2237437723, "lat": 30.797725, "lon": -81.9864591}, {"type": "node", "id": 2237437725, "lat": 30.7978083, "lon": -81.9862847}, {"type": "node", "id": 2237437727, "lat": 30.7981001, "lon": -81.9867601}, {"type": "node", "id": 2237437728, "lat": 30.7983174, "lon": -81.9867011}, {"type": "node", "id": 2237437729, "lat": 30.7983949, "lon": -81.9870175}, {"type": "node", "id": 2237437732, "lat": 30.7986561, "lon": -81.9872639}, {"type": "node", "id": 2237437736, "lat": 30.8002183, "lon": -81.9888298}, {"type": "node", "id": 2237437738, "lat": 30.8032398, "lon": -81.9918637}, {"type": "node", "id": 2237437739, "lat": 30.8034378, "lon": -81.9920678}, {"type": "node", "id": 2237437740, "lat": 30.8035614, "lon": -81.9919129}, {"type": "node", "id": 2237437745, "lat": 30.8055709, "lon": -81.9942146}, {"type": "node", "id": 2237437747, "lat": 30.8064629, "lon": -81.995104}, {"type": "node", "id": 2237437749, "lat": 30.8068514, "lon": -81.9954674}, {"type": "node", "id": 2237437751, "lat": 30.8072841, "lon": -81.9958277}, {"type": "node", "id": 2237437753, "lat": 30.807623, "lon": -81.9960866}, {"type": "node", "id": 2237437755, "lat": 30.8076317, "lon": -81.9958474}, {"type": "node", "id": 2237437757, "lat": 30.8084449, "lon": -81.9966349}, {"type": "node", "id": 2237437759, "lat": 30.8088253, "lon": -81.9968439}, {"type": "node", "id": 2237437761, "lat": 30.8090877, "lon": -81.9967539}, {"type": "node", "id": 2237437762, "lat": 30.8093544, "lon": -81.9971075}, {"type": "node", "id": 2237437763, "lat": 30.8103136, "lon": -81.9973306}, {"type": "node", "id": 2237437764, "lat": 30.8105239, "lon": -81.9976472}, {"type": "node", "id": 2237437765, "lat": 30.81119, "lon": -81.9975249}, {"type": "node", "id": 2237437767, "lat": 30.8113924, "lon": -81.9980399}, {"type": "node", "id": 2237437768, "lat": 30.8114525, "lon": -81.9978455}, {"type": "node", "id": 2237437772, "lat": 30.811491, "lon": -81.9978629}, {"type": "node", "id": 2237437784, "lat": 30.8115837, "lon": -81.9975544}, {"type": "node", "id": 2237437792, "lat": 30.8116585, "lon": -81.9975682}, {"type": "node", "id": 2237437798, "lat": 30.8129323, "lon": -81.9987425}, {"type": "node", "id": 2237437801, "lat": 30.8142008, "lon": -81.9993174}, {"type": "node", "id": 2237437804, "lat": 30.8142652, "lon": -81.9991256}, {"type": "node", "id": 2237437807, "lat": 30.8158665, "lon": -82.0000801}, {"type": "node", "id": 2237437810, "lat": 30.8192462, "lon": -82.0016249}, {"type": "node", "id": 2237437813, "lat": 30.8201259, "lon": -82.0020205}, {"type": "node", "id": 2237437816, "lat": 30.8207374, "lon": -82.0023002}, {"type": "node", "id": 2237437819, "lat": 30.8215066, "lon": -82.0024288}, {"type": "node", "id": 2237437822, "lat": 30.8217314, "lon": -82.0027532}, {"type": "node", "id": 2237437824, "lat": 30.8225288, "lon": -82.0031245}, {"type": "node", "id": 2237437826, "lat": 30.8230047, "lon": -82.0033283}, {"type": "node", "id": 2237437829, "lat": 30.8234314, "lon": -82.0034965}, {"type": "node", "id": 2237437831, "lat": 30.8236952, "lon": -82.00361}, {"type": "node", "id": 2237437834, "lat": 30.8237291, "lon": -82.003493}, {"type": "node", "id": 2237437837, "lat": 30.8238454, "lon": -82.003605}, {"type": "node", "id": 2237437840, "lat": 30.8250559, "lon": -82.0041411}, {"type": "node", "id": 2237437843, "lat": 30.825531, "lon": -82.0043084}, {"type": "node", "id": 2237437847, "lat": 30.8291389, "lon": -82.0054186}, {"type": "node", "id": 2237437850, "lat": 30.8295163, "lon": -82.0055348}, {"type": "node", "id": 2237437853, "lat": 30.8295382, "lon": -82.0055415, "tags": {"crossing": "traffic_signals", "highway": "crossing"}}, {"type": "node", "id": 2237437858, "lat": 30.8296729, "lon": -82.0055846, "tags": {"crossing": "traffic_signals", "highway": "crossing"}}, {"type": "node", "id": 2237437863, "lat": 30.8297004, "lon": -82.0055929}, {"type": "node", "id": 2237437866, "lat": 30.8300163, "lon": -82.0056879}, {"type": "node", "id": 2237437868, "lat": 30.8306549, "lon": -82.0058787}, {"type": "node", "id": 2237437870, "lat": 30.8308758, "lon": -82.005941}, {"type": "node", "id": 2237437872, "lat": 30.8310658, "lon": -82.005988}, {"type": "node", "id": 2237437874, "lat": 30.8311472, "lon": -82.0060046}, {"type": "node", "id": 2237437876, "lat": 30.8314769, "lon": -82.006069}, {"type": "node", "id": 2237437879, "lat": 30.8315097, "lon": -82.0060759, "tags": {"crossing": "traffic_signals", "highway": "crossing"}}, {"type": "node", "id": 2237437882, "lat": 30.8317217, "lon": -82.0061274, "tags": {"crossing": "traffic_signals", "highway": "crossing"}}, {"type": "node", "id": 2237437886, "lat": 30.8320958, "lon": -82.0062332}, {"type": "node", "id": 2237437887, "lat": 30.8322714, "lon": -82.006285}, {"type": "node", "id": 2237437888, "lat": 30.8326023, "lon": -82.0063838}, {"type": "node", "id": 2237437889, "lat": 30.8326386, "lon": -82.0063925, "tags": {"crossing": "traffic_signals", "highway": "crossing"}}, {"type": "node", "id": 2237437890, "lat": 30.8327681, "lon": -82.0064326, "tags": {"crossing": "traffic_signals", "highway": "crossing"}}, {"type": "node", "id": 2237437891, "lat": 30.8327895, "lon": -82.0064395}, {"type": "node", "id": 2237437892, "lat": 30.8331246, "lon": -82.0065421}, {"type": "node", "id": 2237437893, "lat": 30.8346234, "lon": -82.0069865}, {"type": "node", "id": 2237437894, "lat": 30.8350266, "lon": -82.0070883}, {"type": "node", "id": 2237437895, "lat": 30.8355389, "lon": -82.0071567}, {"type": "node", "id": 2237437896, "lat": 30.8360201, "lon": -82.0071822}, {"type": "node", "id": 2237437897, "lat": 30.8364241, "lon": -82.0071724}, {"type": "node", "id": 2237437898, "lat": 30.8366533, "lon": -82.0071499}, {"type": "node", "id": 2237437899, "lat": 30.8376934, "lon": -82.0069803}, {"type": "node", "id": 2237437905, "lat": 30.8380848, "lon": -82.0069098}, {"type": "node", "id": 2237437909, "lat": 30.8381678, "lon": -82.006964}, {"type": "node", "id": 2237437911, "lat": 30.8382129, "lon": -82.0069916}, {"type": "node", "id": 2237437913, "lat": 30.8382593, "lon": -82.0070387}, {"type": "node", "id": 2237437916, "lat": 30.8382901, "lon": -82.0070898}, {"type": "node", "id": 2237437921, "lat": 30.8383115, "lon": -82.0071452}, {"type": "node", "id": 2237437933, "lat": 30.8389492, "lon": -82.0066986}, {"type": "node", "id": 2237437935, "lat": 30.8390377, "lon": -82.0068157}, {"type": "node", "id": 2237437937, "lat": 30.8397389, "lon": -82.0067379}, {"type": "node", "id": 2237437940, "lat": 30.8402282, "lon": -82.0067157}, {"type": "node", "id": 2237437957, "lat": 30.8405581, "lon": -82.0067128}, {"type": "node", "id": 2237437985, "lat": 30.840893, "lon": -82.0067169}, {"type": "node", "id": 2237437992, "lat": 30.8411676, "lon": -82.0065318}, {"type": "node", "id": 2237437995, "lat": 30.8412338, "lon": -82.0067266}, {"type": "node", "id": 2237438000, "lat": 30.8413956, "lon": -82.0065373}, {"type": "node", "id": 2237438009, "lat": 30.8415403, "lon": -82.0067404}, {"type": "node", "id": 2237438017, "lat": 30.8418532, "lon": -82.0067695}, {"type": "node", "id": 2237438020, "lat": 30.8420658, "lon": -82.0067888}, {"type": "node", "id": 2237438023, "lat": 30.8424898, "lon": -82.0068414}, {"type": "node", "id": 2237438026, "lat": 30.8428069, "lon": -82.0068898}, {"type": "node", "id": 2237438029, "lat": 30.8431655, "lon": -82.0069576}, {"type": "node", "id": 2237438032, "lat": 30.8436766, "lon": -82.0068632}, {"type": "node", "id": 2237438038, "lat": 30.8441536, "lon": -82.0071831}, {"type": "node", "id": 2237438041, "lat": 30.8444209, "lon": -82.007255}, {"type": "node", "id": 2237438043, "lat": 30.8449584, "lon": -82.0074145}, {"type": "node", "id": 5446934806, "lat": 30.8332457, "lon": -82.0065787}, {"type": "node", "id": 8326661248, "lat": 30.8325197, "lon": -82.0063591}, {"type": "node", "id": 8332691923, "lat": 30.8411062, "lon": -82.006723}, {"type": "node", "id": 8332691924, "lat": 30.8403469, "lon": -82.0067147}, {"type": "node", "id": 8332691925, "lat": 30.8402642, "lon": -82.0067154}, {"type": "node", "id": 8332691932, "lat": 30.8311132, "lon": -82.0059977}, {"type": "node", "id": 8431308151, "lat": 30.8251487, "lon": -82.0041767}, {"type": "node", "id": 8431308154, "lat": 30.8244258, "lon": -82.0038687}, {"type": "node", "id": 8431308158, "lat": 30.8238642, "lon": -82.0036137}, {"type": "node", "id": 8562476785, "lat": 30.8095981, "lon": -81.9970035}, {"type": "node", "id": 8722347009, "lat": 30.8217327, "lon": -82.0025321}, {"type": "node", "id": 8722347015, "lat": 30.8210912, "lon": -82.0022406}, {"type": "node", "id": 8886637251, "lat": 30.8204155, "lon": -82.0019342}, {"type": "node", "id": 8886803183, "lat": 30.8106347, "lon": -81.9976973}, {"type": "node", "id": 8886803190, "lat": 30.8099955, "lon": -81.9974033}, {"type": "node", "id": 8886803202, "lat": 30.8094055, "lon": -81.9971311}, {"type": "node", "id": 8893778087, "lat": 30.8255138, "lon": -82.0043028}, {"type": "node", "id": 8894200643, "lat": 30.8357071, "lon": -82.0071707}, {"type": "node", "id": 8894200646, "lat": 30.8354103, "lon": -82.0071425}, {"type": "node", "id": 8973088623, "lat": 30.8316296, "lon": -82.0061069}, {"type": "node", "id": 9241348871, "lat": 30.7861977, "lon": -81.9810951}, {"type": "node", "id": 9241348886, "lat": 30.7984643, "lon": -81.9869468}, {"type": "node", "id": 9241348887, "lat": 30.7988631, "lon": -81.9873433}, {"type": "node", "id": 9241348888, "lat": 30.8000912, "lon": -81.9886008}, {"type": "node", "id": 9241348889, "lat": 30.7997192, "lon": -81.9881886}, {"type": "node", "id": 9241348890, "lat": 30.7990379, "lon": -81.9875207}, {"type": "node", "id": 9241360761, "lat": 30.8042476, "lon": -81.9926069}, {"type": "node", "id": 9241360762, "lat": 30.8044579, "lon": -81.9929056}, {"type": "node", "id": 9241360763, "lat": 30.8047586, "lon": -81.9932522}, {"type": "node", "id": 9241360764, "lat": 30.8054921, "lon": -81.9939977}, {"type": "node", "id": 9241360765, "lat": 30.8070002, "lon": -81.9955913}, {"type": "node", "id": 9241360766, "lat": 30.8066826, "lon": -81.9952227}, {"type": "node", "id": 9241360767, "lat": 30.8056905, "lon": -81.9941902}, {"type": "node", "id": 9241360991, "lat": 30.819892, "lon": -82.0019153}, {"type": "node", "id": 9241361015, "lat": 30.8225424, "lon": -82.0029022}, {"type": "node", "id": 9241361016, "lat": 30.8224799, "lon": -82.0031017}, {"type": "node", "id": 9241361017, "lat": 30.8234745, "lon": -82.003515}, {"type": "node", "id": 9241361018, "lat": 30.8230618, "lon": -82.0032395}, {"type": "node", "id": 9241361019, "lat": 30.8226142, "lon": -82.0030567}, {"type": "node", "id": 9241361020, "lat": 30.8214818, "lon": -82.0024175}, {"type": "node", "id": 9241361021, "lat": 30.8216891, "lon": -82.0025978}, {"type": "node", "id": 9241361022, "lat": 30.8220198, "lon": -82.0027767}, {"type": "node", "id": 9241361023, "lat": 30.8224038, "lon": -82.0029439}, {"type": "node", "id": 9241361024, "lat": 30.8216787, "lon": -82.0027292}, {"type": "node", "id": 9241361025, "lat": 30.8216357, "lon": -82.0026367}, {"type": "node", "id": 9241361026, "lat": 30.8211915, "lon": -82.0023956}, {"type": "node", "id": 9241361027, "lat": 30.8208876, "lon": -82.0022478}, {"type": "node", "id": 9241361028, "lat": 30.820096, "lon": -82.0018667}, {"type": "node", "id": 9241361029, "lat": 30.8203832, "lon": -82.0020339}, {"type": "node", "id": 9241361030, "lat": 30.8206504, "lon": -82.0021506}, {"type": "node", "id": 9241361031, "lat": 30.8201635, "lon": -82.0020377}, {"type": "node", "id": 9241361032, "lat": 30.8199658, "lon": -82.0018667}, {"type": "node", "id": 9241361033, "lat": 30.8197587, "lon": -82.0017305}, {"type": "node", "id": 9241361034, "lat": 30.8193746, "lon": -82.0015672}, {"type": "node", "id": 9241361035, "lat": 30.8178316, "lon": -82.0008205}, {"type": "node", "id": 9241361036, "lat": 30.8181555, "lon": -82.0010033}, {"type": "node", "id": 9241361037, "lat": 30.8191709, "lon": -82.0014855}, {"type": "node", "id": 9241361038, "lat": 30.8159702, "lon": -82.0001275}, {"type": "node", "id": 9241361045, "lat": 30.8127848, "lon": -81.9986037}, {"type": "node", "id": 9241361046, "lat": 30.8123539, "lon": -81.9983548}, {"type": "node", "id": 9241361047, "lat": 30.8119064, "lon": -81.9981409}, {"type": "node", "id": 9241361048, "lat": 30.8115323, "lon": -81.9979893}, {"type": "node", "id": 9241361049, "lat": 30.8114953, "lon": -81.9979498}, {"type": "node", "id": 9241361050, "lat": 30.8114668, "lon": -81.9979063}, {"type": "node", "id": 9241361051, "lat": 30.8102462, "lon": -81.9972994}, {"type": "node", "id": 9241361052, "lat": 30.8104066, "lon": -81.9974301}, {"type": "node", "id": 9241361053, "lat": 30.8106524, "lon": -81.9975761}, {"type": "node", "id": 9241361054, "lat": 30.8109006, "lon": -81.9977102}, {"type": "node", "id": 9241361055, "lat": 30.8112923, "lon": -81.997886}, {"type": "node", "id": 9241361056, "lat": 30.8101205, "lon": -81.9973366}, {"type": "node", "id": 9241361057, "lat": 30.8095138, "lon": -81.9970656}, {"type": "node", "id": 9241361058, "lat": 30.8079173, "lon": -81.9960514}, {"type": "node", "id": 9241361059, "lat": 30.8080944, "lon": -81.9962393}, {"type": "node", "id": 9241361060, "lat": 30.8083615, "lon": -81.9964614}, {"type": "node", "id": 9241361061, "lat": 30.8087087, "lon": -81.9966569}, {"type": "node", "id": 9241361062, "lat": 30.8092849, "lon": -81.9969679}, {"type": "node", "id": 9241361088, "lat": 30.8247814, "lon": -82.0040255}, {"type": "node", "id": 9241361129, "lat": 30.8269052, "lon": -82.0047301}, {"type": "node", "id": 9241361131, "lat": 30.8272388, "lon": -82.0048338}, {"type": "node", "id": 9241361175, "lat": 30.8339229, "lon": -82.0067819}, {"type": "node", "id": 9241361183, "lat": 30.8342854, "lon": -82.0068881}, {"type": "node", "id": 10286354026, "lat": 30.8384078, "lon": -82.0068593}, {"type": "node", "id": 11891622893, "lat": 30.8345073, "lon": -82.0069536}, {"type": "node", "id": 11891622903, "lat": 30.8347921, "lon": -82.0070295}, {"type": "node", "id": 11891622912, "lat": 30.8355581, "lon": -82.0071583}, {"type": "node", "id": 11891622948, "lat": 30.8352551, "lon": -82.0071244}, {"type": "node", "id": 11891622949, "lat": 30.8329353, "lon": -82.0064841}, {"type": "node", "id": 11891623032, "lat": 30.8353184, "lon": -82.0071323}, {"type": "way", "id": 9083549, "nodes": [2237437840, 8431308151, 66996882, 8893778087, 2237437843, 67066309], "tags": {"HFCS": "Principal Arterial - Other", "NHS": "yes", "fixme": "Does the road name really have \"South\" in it here? Doesn't seem to match up with the rest of the road grid here.", "gdot:grip": "US 1/SR 17", "hgv": "designated", "highway": "trunk", "lanes": "5", "lanes:backward": "2", "lanes:both_ways": "1", "lanes:forward": "2", "maxspeed": "35 mph", "name": "South 2nd Street", "ref": "US 1;US 23;US 301;GA 4;GA 15", "source:hgv": "https://gamccd.net/Documents/OSP_GaOversizeTrkRouteMap.pdf", "turn:lanes:both_ways": "left"}}, {"type": "way", "id": 9084780, "nodes": [2237437837, 8431308158], "tags": {"HFCS": "Principal Arterial - Other", "NHS": "yes", "gdot:grip": "US 1/SR 17", "hgv": "designated", "highway": "trunk", "lanes": "4", "maxspeed": "45 mph", "name": "2nd Street", "ref": "US 1;US 23;US 301;GA 4;GA 15", "source:hgv": "https://gamccd.net/Documents/OSP_GaOversizeTrkRouteMap.pdf"}}, {"type": "way", "id": 9084785, "nodes": [67066309, 9241361129, 9241361131, 67071538, 67067471, 67068597, 2237437847], "tags": {"HFCS": "Principal Arterial - Other", "NHS": "yes", "gdot:grip": "US 1/SR 17", "hgv": "designated", "highway": "trunk", "lanes": "5", "lanes:backward": "2", "lanes:both_ways": "1", "lanes:forward": "2", "maxspeed": "35 mph", "name": "Second Street", "ref": "US 1;US 23;US 301;GA 4;GA 15", "source:hgv": "https://gamccd.net/Documents/OSP_GaOversizeTrkRouteMap.pdf", "turn:lanes:both_ways": "left"}}, {"type": "way", "id": 195045662, "nodes": [67066557, 2237437768, 2237437772, 67055591, 2237437804, 67084993, 67020355, 67036030], "tags": {"HFCS": "Principal Arterial - Other", "NHS": "yes", "expressway": "yes", "gdot:grip": "US 1/SR 17", "hgv": "designated", "highway": "trunk", "lanes": "2", "maxspeed": "55 mph", "oneway": "yes", "ref": "US 1;US 23;US 301;GA 4;GA 15", "source:hgv": "https://gamccd.net/Documents/OSP_GaOversizeTrkRouteMap.pdf", "start_date": "1955"}}, {"type": "way", "id": 195045667, "nodes": [2055464014, 67084867, 2237437706, 67022277, 67008641, 67084873, 67084879, 67084887, 67044868, 67084891, 67084897], "tags": {"HFCS": "Principal Arterial - Other", "NHS": "yes", "expressway": "yes", "gdot:grip": "US 1/SR 17", "hgv": "designated", "highway": "trunk", "lanes": "2", "maxspeed": "55 mph", "note": "\"start_date\" is when this roadway was first improved (widened, straighted, surfaced, bridges, etc), not when it was first built", "oneway": "yes", "ref": "US 1;US 23;US 301;GA 4;GA 15", "source:hgv": "https://gamccd.net/Documents/OSP_GaOversizeTrkRouteMap.pdf", "start_date": "1955"}}, {"type": "way", "id": 214138044, "nodes": [2237437767, 8886803183, 2237437764, 8886803190, 8886803202, 2237437762, 2237437759, 2237437757, 67031435, 2237437753, 2237437751, 9241360765, 2237437749, 2237437747, 2237437745, 2237437739], "tags": {"HFCS": "Principal Arterial - Other", "NHS": "yes", "expressway": "yes", "gdot:grip": "US 1/SR 17", "hgv": "designated", "highway": "trunk", "lanes": "2", "maxspeed": "55 mph", "oneway": "yes", "ref": "US 1;US 23;US 301;GA 4;GA 15", "source:hgv": "https://gamccd.net/Documents/OSP_GaOversizeTrkRouteMap.pdf", "start_date": "1955"}}, {"type": "way", "id": 214138045, "nodes": [2237437719, 2237437718, 2237437717, 2237437716, 2237437714, 2237437712, 2237437710, 2237437708, 2237437707, 2237437705, 9241348871, 2237437687, 2237437686, 2237437682], "tags": {"HFCS": "Principal Arterial - Other", "NHS": "yes", "expressway": "yes", "gdot:grip": "US 1/SR 17", "hgv": "designated", "highway": "trunk", "lanes": "2", "maxspeed": "55 mph", "oneway": "yes", "ref": "US 1;US 23;US 301;GA 4;GA 15", "source:hgv": "https://gamccd.net/Documents/OSP_GaOversizeTrkRouteMap.pdf", "start_date": "1955"}}, {"type": "way", "id": 214138046, "nodes": [2237437740, 9241360761, 67084948, 67035495, 67084957, 67084963, 67084970, 67084973, 2237437755, 67084978, 9241361058, 67084981, 67084983, 2237437761, 67031268, 8562476785, 67084986, 9241361051, 2237437763, 67066557], "tags": {"HFCS": "Principal Arterial - Other", "NHS": "yes", "expressway": "yes", "gdot:grip": "US 1/SR 17", "hgv": "designated", "highway": "trunk", "lanes": "2", "maxspeed": "55 mph", "note": "\"start_date\" is when this roadway was first improved (widened, straighted, surfaced, bridges, etc), not when it was first built", "oneway": "yes", "ref": "US 1;US 23;US 301;GA 4;GA 15", "source:hgv": "https://gamccd.net/Documents/OSP_GaOversizeTrkRouteMap.pdf", "start_date": "1955"}}, {"type": "way", "id": 214138048, "nodes": [67084941, 2237437740], "tags": {"HFCS": "Principal Arterial - Other", "NHS": "yes", "bridge": "yes", "expressway": "yes", "gdot:grip": "US 1/SR 17", "hgv": "designated", "highway": "trunk", "lanes": "2", "layer": "1", "maxspeed": "55 mph", "note": "\"start_date\" is when this roadway was first improved (widened, straighted, surfaced, bridges, etc), not when it was first built", "oneway": "yes", "ref": "US 1;US 23;US 301;GA 4;GA 15", "source:hgv": "https://gamccd.net/Documents/OSP_GaOversizeTrkRouteMap.pdf", "start_date": "1955"}}, {"type": "way", "id": 214138050, "nodes": [2237437739, 2237437738], "tags": {"HFCS": "Principal Arterial - Other", "NHS": "yes", "bridge": "yes", "expressway": "yes", "gdot:grip": "US 1/SR 17", "hgv": "designated", "highway": "trunk", "lanes": "2", "layer": "1", "maxspeed": "55 mph", "oneway": "yes", "ref": "US 1;US 23;US 301;GA 4;GA 15", "source:hgv": "https://gamccd.net/Documents/OSP_GaOversizeTrkRouteMap.pdf", "start_date": "1955"}}, {"type": "way", "id": 214138052, "nodes": [67085022, 67085019], "tags": {"HFCS": "Principal Arterial - Other", "NHS": "yes", "dual_carriageway": "yes", "expressway": "yes", "gdot:grip": "US 1/SR 17", "hgv": "designated", "highway": "trunk", "lanes": "3", "maxspeed": "45 mph", "oneway": "yes", "placement": "right_of:1", "ref": "US 1;US 23;US 301;GA 4;GA 15;GA 23;GA 121", "source:hgv": "https://gamccd.net/Documents/OSP_GaOversizeTrkRouteMap.pdf", "start_date": "1947", "surface": "asphalt", "turn:lanes": "||right"}}, {"type": "way", "id": 214138054, "nodes": [67084897, 67084902, 2237437725], "tags": {"HFCS": "Principal Arterial - Other", "NHS": "yes", "bridge": "yes", "expressway": "yes", "gdot:grip": "US 1/SR 17", "hgv": "designated", "highway": "trunk", "lanes": "2", "layer": "1", "maxspeed": "55 mph", "note": "\"start_date\" is when this roadway was first improved (widened, straighted, surfaced, bridges, etc), not when it was first built", "oneway": "yes", "ref": "US 1;US 23;US 301;GA 4;GA 15", "source:hgv": "https://gamccd.net/Documents/OSP_GaOversizeTrkRouteMap.pdf", "start_date": "1955"}}, {"type": "way", "id": 214138055, "nodes": [2237437723, 2237437721, 2237437719], "tags": {"HFCS": "Principal Arterial - Other", "NHS": "yes", "bridge": "yes", "expressway": "yes", "gdot:grip": "US 1/SR 17", "hgv": "designated", "highway": "trunk", "lanes": "2", "layer": "1", "maxspeed": "55 mph", "oneway": "yes", "ref": "US 1;US 23;US 301;GA 4;GA 15", "source:hgv": "https://gamccd.net/Documents/OSP_GaOversizeTrkRouteMap.pdf", "start_date": "1955"}}, {"type": "way", "id": 214138056, "nodes": [2237437738, 2237437736, 67034139, 2237437732, 2237437729, 2237437727, 2237437723], "tags": {"HFCS": "Principal Arterial - Other", "NHS": "yes", "expressway": "yes", "gdot:grip": "US 1/SR 17", "hgv": "designated", "highway": "trunk", "lanes": "2", "maxspeed": "55 mph", "oneway": "yes", "ref": "US 1;US 23;US 301;GA 4;GA 15", "source:hgv": "https://gamccd.net/Documents/OSP_GaOversizeTrkRouteMap.pdf", "start_date": "1955"}}, {"type": "way", "id": 214138058, "nodes": [2237437725, 67084912, 2237437728, 67084917, 67084922, 67034140, 67084934, 67084941], "tags": {"HFCS": "Principal Arterial - Other", "NHS": "yes", "expressway": "yes", "gdot:grip": "US 1/SR 17", "hgv": "designated", "highway": "trunk", "lanes": "2", "maxspeed": "55 mph", "note": "\"start_date\" is when this roadway was first improved (widened, straighted, surfaced, bridges, etc), not when it was first built", "oneway": "yes", "ref": "US 1;US 23;US 301;GA 4;GA 15", "source:hgv": "https://gamccd.net/Documents/OSP_GaOversizeTrkRouteMap.pdf", "start_date": "1955"}}, {"type": "way", "id": 214138061, "nodes": [9241360991, 2237437810, 9241361038, 2237437807, 2237437801, 67053123, 2237437798, 2237437767], "tags": {"HFCS": "Principal Arterial - Other", "NHS": "yes", "expressway": "yes", "gdot:grip": "US 1/SR 17", "hgv": "designated", "highway": "trunk", "lanes": "2", "maxspeed": "55 mph", "oneway": "yes", "ref": "US 1;US 23;US 301;GA 4;GA 15", "source:hgv": "https://gamccd.net/Documents/OSP_GaOversizeTrkRouteMap.pdf", "start_date": "1955"}}, {"type": "way", "id": 214138081, "nodes": [67020355, 2237437810], "tags": {"highway": "trunk_link"}}, {"type": "way", "id": 214138087, "nodes": [2237437816, 67071964], "tags": {"highway": "trunk_link"}}, {"type": "way", "id": 214138090, "nodes": [2237437804, 2237437801], "tags": {"highway": "trunk_link"}}, {"type": "way", "id": 214138093, "nodes": [2237437762, 67031268], "tags": {"highway": "trunk_link"}}, {"type": "way", "id": 214138095, "nodes": [67034140, 67034139], "tags": {"highway": "trunk_link", "tiger:cfcc": "A41", "tiger:county": "Charlton, GA", "tiger:reviewed": "no"}}, {"type": "way", "id": 214138106, "nodes": [67066557, 384421823, 2237437765, 2237437784, 2237437792], "tags": {"hgv": "designated", "highway": "trunk_link", "lanes": "1", "old_ref": "US 1", "oneway": "yes", "source:hgv": "https://gamccd.net/Documents/OSP_GaOversizeTrkRouteMap.pdf", "tiger:cfcc": "A41", "tiger:county": "Charlton, GA", "tiger:name_base": "Old US Hwy 1"}}, {"type": "way", "id": 214138120, "nodes": [663340665, 2237437921, 2237437916, 2237437913, 2237437911, 2237437909, 2237437905], "tags": {"highway": "trunk_link", "lanes": "1", "oneway": "yes"}}, {"type": "way", "id": 214138127, "nodes": [67070812, 9241361175, 9241361183, 67071974, 11891622893, 2237437893, 11891622903, 67071976, 2237437894, 11891622948], "tags": {"HFCS": "Principal Arterial - Other", "NHS": "yes", "gdot:grip": "US 1/SR 17", "hgv": "designated", "highway": "trunk", "lanes": "5", "lanes:backward": "2", "lanes:both_ways": "1", "lanes:forward": "2", "maxspeed": "35 mph", "name": "Second Street", "ref": "US 1;US 23;US 301;GA 4;GA 15", "source:hgv": "https://gamccd.net/Documents/OSP_GaOversizeTrkRouteMap.pdf", "start_date": "1947", "surface": "asphalt", "turn:lanes:both_ways": "left"}}, {"type": "way", "id": 214138128, "nodes": [2237437886, 2237437887], "tags": {"HFCS": "Principal Arterial - Other", "NHS": "yes", "gdot:grip": "US 1/SR 17", "hgv": "designated", "highway": "trunk", "lanes": "5", "lanes:backward": "2", "lanes:both_ways": "1", "lanes:forward": "2", "maxspeed": "35 mph", "name": "Second Street", "ref": "US 1;US 23;US 301;GA 4;GA 15", "source:hgv": "https://gamccd.net/Documents/OSP_GaOversizeTrkRouteMap.pdf", "turn:lanes:both_ways": "left"}}, {"type": "way", "id": 214138131, "nodes": [2237437899, 2237437905], "tags": {"HFCS": "Principal Arterial - Other", "NHS": "yes", "gdot:grip": "US 1/SR 17", "hgv": "designated", "highway": "trunk", "lanes": "4", "lanes:backward": "2", "lanes:forward": "2", "maxspeed": "45 mph", "name": "2nd Street", "ref": "US 1;US 23;US 301;GA 4;GA 15", "source:hgv": "https://gamccd.net/Documents/OSP_GaOversizeTrkRouteMap.pdf", "start_date": "1947", "surface": "asphalt"}}, {"type": "way", "id": 214138133, "nodes": [2237437866, 67071028, 2237437868, 2237437870, 2237437872, 8332691932, 2237437874], "tags": {"HFCS": "Principal Arterial - Other", "NHS": "yes", "gdot:grip": "US 1/SR 17", "hgv": "designated", "highway": "trunk", "lanes": "5", "lanes:backward": "2", "lanes:both_ways": "1", "lanes:forward": "2", "maxspeed": "35 mph", "name": "Second Street", "ref": "US 1;US 23;US 301;GA 4;GA 15", "source:hgv": "https://gamccd.net/Documents/OSP_GaOversizeTrkRouteMap.pdf", "turn:lanes:both_ways": "left"}}, {"type": "way", "id": 214138134, "nodes": [2237437874, 2237437876, 2237437879, 8973088623], "tags": {"HFCS": "Principal Arterial - Other", "NHS": "yes", "gdot:grip": "US 1/SR 17", "hgv": "designated", "highway": "trunk", "lanes": "4", "maxspeed": "35 mph", "name": "Second Street", "ref": "US 1;US 23;US 301;GA 4;GA 15", "source:hgv": "https://gamccd.net/Documents/OSP_GaOversizeTrkRouteMap.pdf"}}, {"type": "way", "id": 214138136, "nodes": [2237437847, 2237437850, 2237437853, 67071534, 2237437858, 2237437863, 2237437866], "tags": {"HFCS": "Principal Arterial - Other", "NHS": "yes", "gdot:grip": "US 1/SR 17", "hgv": "designated", "highway": "trunk", "lanes": "4", "maxspeed": "35 mph", "name": "Second Street", "ref": "US 1;US 23;US 301;GA 4;GA 15", "source:hgv": "https://gamccd.net/Documents/OSP_GaOversizeTrkRouteMap.pdf"}}, {"type": "way", "id": 214138138, "nodes": [2237437837, 2237437831, 9241361017, 2237437829, 2237437826, 2237437824, 9241361016, 2237437822, 9241361024, 2237437816], "tags": {"HFCS": "Principal Arterial - Other", "NHS": "yes", "expressway": "yes", "gdot:grip": "US 1/SR 17", "hgv": "designated", "highway": "trunk", "lanes": "2", "maxspeed": "45 mph", "name": "2nd Street", "oneway": "yes", "ref": "US 1;US 23;US 301;GA 4;GA 15", "source:hgv": "https://gamccd.net/Documents/OSP_GaOversizeTrkRouteMap.pdf", "start_date": "1955"}}, {"type": "way", "id": 214138140, "nodes": [67071964, 8722347015, 9241361020, 2237437819, 8722347009, 9241361015, 67024904, 67071967, 67061896, 2237437834, 2237437837], "tags": {"HFCS": "Principal Arterial - Other", "NHS": "yes", "expressway": "yes", "gdot:grip": "US 1/SR 17", "hgv": "designated", "highway": "trunk", "lanes": "2", "maxspeed": "45 mph", "name": "2nd Street", "oneway": "yes", "ref": "US 1;US 23;US 301;GA 4;GA 15", "source:hgv": "https://gamccd.net/Documents/OSP_GaOversizeTrkRouteMap.pdf", "start_date": "1955"}}, {"type": "way", "id": 214138141, "nodes": [2237437887, 8326661248, 2237437888, 2237437889, 66981852, 2237437890, 2237437891, 11891622949], "tags": {"HFCS": "Principal Arterial - Other", "NHS": "yes", "gdot:grip": "US 1/SR 17", "hgv": "designated", "highway": "trunk", "lanes": "4", "maxspeed": "35 mph", "name": "Second Street", "ref": "US 1;US 23;US 301;GA 4;GA 15", "source:hgv": "https://gamccd.net/Documents/OSP_GaOversizeTrkRouteMap.pdf"}}, {"type": "way", "id": 294212576, "nodes": [8973088623, 2237437882, 2237437886], "tags": {"HFCS": "Principal Arterial - Other", "NHS": "yes", "gdot:grip": "US 1/SR 17", "hgv": "designated", "highway": "trunk", "lanes": "4", "maxspeed": "35 mph", "name": "Second Street", "ref": "US 1;US 23;US 301;GA 4;GA 15", "source:hgv": "https://gamccd.net/Documents/OSP_GaOversizeTrkRouteMap.pdf"}}, {"type": "way", "id": 1001180417, "nodes": [2237437728, 9241348886, 9241348887, 67034139], "tags": {"highway": "trunk_link", "lanes": "1", "maxspeed": "65 mph", "oneway": "yes", "turn": "reverse"}}, {"type": "way", "id": 1001180418, "nodes": [2237437736, 9241348888, 9241348889, 9241348890, 67034140], "tags": {"highway": "trunk_link", "lanes": "1", "maxspeed": "65 mph", "oneway": "yes", "turn": "reverse"}}, {"type": "way", "id": 1001180426, "nodes": [9241360761, 9241360762, 9241360763, 9241360764, 2237437745], "tags": {"highway": "trunk_link", "lanes": "1", "oneway": "yes", "turn": "reverse"}}, {"type": "way", "id": 1001180427, "nodes": [9241360765, 9241360766, 9241360767, 67035495], "tags": {"highway": "trunk_link", "lanes": "1", "oneway": "yes", "turn": "reverse"}}, {"type": "way", "id": 1001180454, "nodes": [67036030, 8886637251, 67071964], "tags": {"HFCS": "Principal Arterial - Other", "NHS": "yes", "expressway": "yes", "gdot:grip": "US 1/SR 17", "hgv": "designated", "highway": "trunk", "lanes": "2", "maxspeed": "45 mph", "oneway": "yes", "ref": "US 1;US 23;US 301;GA 4;GA 15", "source:hgv": "https://gamccd.net/Documents/OSP_GaOversizeTrkRouteMap.pdf", "start_date": "1955"}}, {"type": "way", "id": 1001180455, "nodes": [2237437816, 9241361031, 2237437813, 9241360991], "tags": {"HFCS": "Principal Arterial - Other", "NHS": "yes", "expressway": "yes", "gdot:grip": "US 1/SR 17", "hgv": "designated", "highway": "trunk", "lanes": "2", "maxspeed": "45 mph", "oneway": "yes", "ref": "US 1;US 23;US 301;GA 4;GA 15", "source:hgv": "https://gamccd.net/Documents/OSP_GaOversizeTrkRouteMap.pdf", "start_date": "1955"}}, {"type": "way", "id": 1001180459, "nodes": [9241361015, 9241361016], "tags": {"highway": "trunk_link"}}, {"type": "way", "id": 1001180460, "nodes": [9241361017, 9241361018, 9241361019, 9241361015], "tags": {"highway": "trunk_link", "lanes": "1", "oneway": "yes", "turn": "reverse"}}, {"type": "way", "id": 1001180461, "nodes": [9241361020, 9241361021, 9241361022, 9241361023, 9241361016], "tags": {"highway": "trunk_link", "lanes": "1", "oneway": "yes", "turn": "reverse"}}, {"type": "way", "id": 1001180462, "nodes": [9241361024, 9241361025, 9241361026, 9241361027, 67071964], "tags": {"highway": "trunk_link", "lanes": "1", "oneway": "yes", "turn": "reverse"}}, {"type": "way", "id": 1001180463, "nodes": [67036030, 9241361028, 9241361029, 9241361030, 2237437816], "tags": {"highway": "trunk_link", "lanes": "1", "oneway": "yes", "turn": "reverse"}}, {"type": "way", "id": 1001180464, "nodes": [9241361031, 9241361032, 9241361033, 9241361034, 67020355], "tags": {"highway": "trunk_link", "lanes": "1", "oneway": "yes", "turn": "reverse"}}, {"type": "way", "id": 1001180465, "nodes": [67084993, 9241361035, 9241361036, 9241361037, 2237437810], "tags": {"highway": "trunk_link", "lanes": "1", "oneway": "yes", "turn": "reverse"}}, {"type": "way", "id": 1001180468, "nodes": [2237437798, 9241361045, 9241361046, 9241361047, 9241361048, 9241361049, 9241361050, 2237437768], "tags": {"highway": "trunk_link", "lanes": "1", "oneway": "yes", "turn": "reverse"}}, {"type": "way", "id": 1001180469, "nodes": [9241361051, 9241361052, 9241361053, 9241361054, 9241361055, 2237437767], "tags": {"highway": "trunk_link", "lanes": "1", "oneway": "yes", "turn": "reverse"}}, {"type": "way", "id": 1001180470, "nodes": [2237437764, 9241361056, 9241361057, 67031268], "tags": {"highway": "trunk_link", "lanes": "1", "oneway": "yes", "turn": "reverse"}}, {"type": "way", "id": 1001180471, "nodes": [9241361058, 9241361059, 9241361060, 9241361061, 9241361062, 2237437762], "tags": {"highway": "trunk_link", "lanes": "1", "oneway": "yes", "turn": "reverse"}}, {"type": "way", "id": 1001180474, "nodes": [8431308158, 67066302], "tags": {"HFCS": "Principal Arterial - Other", "NHS": "yes", "gdot:grip": "US 1/SR 17", "hgv": "designated", "highway": "trunk", "lanes": "5", "lanes:backward": "2", "lanes:both_ways": "1", "lanes:forward": "2", "maxspeed": "45 mph", "name": "2nd Street", "ref": "US 1;US 23;US 301;GA 4;GA 15", "source:hgv": "https://gamccd.net/Documents/OSP_GaOversizeTrkRouteMap.pdf", "turn:lanes:both_ways": "left"}}, {"type": "way", "id": 1001180484, "nodes": [67066302, 67066306, 8431308154, 9241361088, 67031783, 2237437840], "tags": {"HFCS": "Principal Arterial - Other", "NHS": "yes", "fixme": "Does the road name really have \"South\" in it here? Doesn't seem to match up with the rest of the road grid here.", "gdot:grip": "US 1/SR 17", "hgv": "designated", "highway": "trunk", "lanes": "5", "lanes:backward": "2", "lanes:both_ways": "1", "lanes:forward": "2", "name": "South 2nd Street", "ref": "US 1; US 23; US 301; GA 4; GA 15", "source:hgv": "https://gamccd.net/Documents/OSP_GaOversizeTrkRouteMap.pdf", "tiger:cfcc": "A21", "tiger:county": "Charlton, GA", "tiger:name_base": "2nd", "tiger:name_base_1": "United States Highway 23", "tiger:name_base_2": "United States Highway 301", "tiger:name_base_3": "United States Highway 1", "tiger:name_base_4": "State Route 15", "tiger:name_direction_prefix": "S", "tiger:name_type": "St", "tiger:zip_left": "31537", "turn:lanes:both_ways": "left"}}, {"type": "way", "id": 1124849255, "nodes": [10286354026, 67085019], "tags": {"HFCS": "Principal Arterial - Other", "NHS": "yes", "gdot:grip": "US 1/SR 17", "hgv": "designated", "highway": "trunk", "lanes": "6", "lanes:backward": "3", "lanes:both_ways": "1", "lanes:forward": "2", "maxspeed": "45 mph", "name": "2nd Street", "placement:both_ways": "middle_of:1", "ref": "US 1;US 23;US 301;GA 4;GA 15;GA 23;GA 121", "source:hgv": "https://gamccd.net/Documents/OSP_GaOversizeTrkRouteMap.pdf", "start_date": "1947", "turn:lanes:backward": "||right", "turn:lanes:both_ways": "left"}}, {"type": "way", "id": 1176124227, "nodes": [2237438043, 2237438041, 2237438038, 67024388, 67070350, 2237438029, 2237438026, 2237438023, 2237438020, 2237438017, 2237438009, 2237437995, 8332691923, 2237437985, 2237437957, 8332691924, 8332691925, 2237437940, 2237437937, 67007802, 2237437935], "tags": {"HFCS": "Principal Arterial - Other", "NHS": "yes", "dual_carriageway": "yes", "expressway": "yes", "gdot:grip": "US 1/SR 17", "hgv": "designated", "highway": "trunk", "lanes": "2", "maxspeed": "45 mph", "oneway": "yes", "ref": "US 1;US 23;US 301;GA 4;GA 15;GA 23;GA 121", "source:hgv": "https://gamccd.net/Documents/OSP_GaOversizeTrkRouteMap.pdf", "start_date": "1947", "surface": "asphalt"}}, {"type": "way", "id": 1176124228, "nodes": [67085019, 2237437933, 67085023, 67085024, 67045884, 67085025, 2237437992, 2237438000, 67019727, 67085028, 67085031, 67085035, 67085038, 67085042, 2237438032, 67033317, 67085045, 67085047], "tags": {"HFCS": "Principal Arterial - Other", "NHS": "yes", "dual_carriageway": "yes", "expressway": "yes", "gdot:grip": "US 1/SR 17", "hgv": "designated", "highway": "trunk", "lanes": "2", "maxspeed": "45 mph", "oneway": "yes", "ref": "US 1;US 23;US 301;GA 4;GA 15;GA 23;GA 121", "source:hgv": "https://gamccd.net/Documents/OSP_GaOversizeTrkRouteMap.pdf", "surface": "asphalt"}}, {"type": "way", "id": 1176124229, "nodes": [2237437935, 67085022], "tags": {"HFCS": "Principal Arterial - Other", "NHS": "yes", "dual_carriageway": "yes", "expressway": "yes", "gdot:grip": "US 1/SR 17", "hgv": "designated", "highway": "trunk", "lanes": "3", "maxspeed": "45 mph", "oneway": "yes", "placement": "right_of:1", "ref": "US 1;US 23;US 301;GA 4;GA 15;GA 23;GA 121", "source:hgv": "https://gamccd.net/Documents/OSP_GaOversizeTrkRouteMap.pdf", "surface": "asphalt", "turn:lanes": "||right"}}, {"type": "way", "id": 1176124230, "nodes": [2237437905, 10286354026], "tags": {"HFCS": "Principal Arterial - Other", "NHS": "yes", "gdot:grip": "US 1/SR 17", "hgv": "designated", "highway": "trunk", "lanes": "5", "lanes:backward": "2", "lanes:forward": "3", "maxspeed": "45 mph", "name": "2nd Street", "ref": "US 1;US 23;US 301;GA 4;GA 15", "source:hgv": "https://gamccd.net/Documents/OSP_GaOversizeTrkRouteMap.pdf", "start_date": "1947", "turn:lanes:forward": "left||"}}, {"type": "way", "id": 1281195200, "nodes": [11891622912, 8894200643, 67071980, 2237437896, 67071983, 2237437897, 2237437898, 67071985, 2237437899], "tags": {"HFCS": "Principal Arterial - Other", "NHS": "yes", "gdot:grip": "US 1/SR 17", "hgv": "designated", "highway": "trunk", "lanes": "5", "lanes:backward": "2", "lanes:both_ways": "1", "lanes:forward": "2", "maxspeed": "35 mph", "name": "Second Street", "ref": "US 1;US 23;US 301;GA 4;GA 15", "source:hgv": "https://gamccd.net/Documents/OSP_GaOversizeTrkRouteMap.pdf", "start_date": "1947", "surface": "asphalt", "turn:lanes:both_ways": "left"}}, {"type": "way", "id": 1281195201, "nodes": [11891622948, 67071978, 11891623032, 8894200646, 2237437895, 11891622912], "tags": {"HFCS": "Principal Arterial - Other", "NHS": "yes", "gdot:grip": "US 1/SR 17", "hgv": "designated", "highway": "trunk", "lanes": "5", "lanes:backward": "2", "lanes:both_ways": "1", "lanes:forward": "3", "maxspeed": "35 mph", "name": "Second Street", "ref": "US 1;US 23;US 301;GA 4;GA 15", "source:hgv": "https://gamccd.net/Documents/OSP_GaOversizeTrkRouteMap.pdf", "start_date": "1947", "surface": "asphalt", "turn:lanes:both_ways": "left", "turn:lanes:forward": "none|none|right"}}, {"type": "way", "id": 1281195202, "nodes": [11891622949, 2237437892, 5446934806], "tags": {"HFCS": "Principal Arterial - Other", "NHS": "yes", "gdot:grip": "US 1/SR 17", "hgv": "designated", "highway": "trunk", "lanes": "6", "lanes:backward": "2", "lanes:both_ways": "1", "lanes:forward": "3", "maxspeed": "35 mph", "name": "Second Street", "ref": "US 1;US 23;US 301;GA 4;GA 15", "source:hgv": "https://gamccd.net/Documents/OSP_GaOversizeTrkRouteMap.pdf", "start_date": "1947", "surface": "asphalt", "turn:lanes:both_ways": "left", "turn:lanes:forward": "none|none|right"}}, {"type": "way", "id": 1281195248, "nodes": [5446934806, 67070812], "tags": {"HFCS": "Principal Arterial - Other", "NHS": "yes", "gdot:grip": "US 1/SR 17", "hgv": "designated", "highway": "trunk", "lanes": "5", "lanes:backward": "2", "lanes:both_ways": "1", "lanes:forward": "2", "maxspeed": "35 mph", "name": "Second Street", "ref": "US 1;US 23;US 301;GA 4;GA 15", "source:hgv": "https://gamccd.net/Documents/OSP_GaOversizeTrkRouteMap.pdf", "start_date": "1947", "surface": "asphalt", "turn:lanes:both_ways": "left"}}]}